{
"type": "FeatureCollection",
"features": [
{ "type": "Feature", "properties": { "Description": "Toilette Ottmachauer Steig (oberhalb Badestelle Ostufer)", "isHandicappedAccessible": 0 }, "geometry": { "type": "Point", "coordinates": [ 13.240574813, 52.453581173 ] } },
{ "type": "Feature", "properties": { "Description": "Toilette Uferweg ", "isHandicappedAccessible": 0 }, "geometry": { "type": "Point", "coordinates": [ 13.1992287644287, 52.4365068880875 ] } },
{ "type": "Feature", "properties": { "Description": "Toilette Am Kiesteich 50", "isHandicappedAccessible": 0 }, "geometry": { "type": "Point", "coordinates": [ 13.1648593254089, 52.548839880319598 ] } },
{ "type": "Feature", "properties": { "Description": "Wall CT, Hubertusdamm", "isHandicappedAccessible": 1 }, "geometry": { "type": "Point", "coordinates": [ 13.4711982596938, 52.615670613825998 ] } },
{ "type": "Feature", "properties": { "Description": "Wall CT, Lindenufer", "isHandicappedAccessible": 1 }, "geometry": { "type": "Point", "coordinates": [ 13.2077640060379, 52.537351114776001 ] } },
{ "type": "Feature", "properties": { "Description": "Wall CT, Dubliner Str.", "isHandicappedAccessible": 1 }, "geometry": { "type": "Point", "coordinates": [ 13.3467597533333, 52.560541718478397 ] } },
{ "type": "Feature", "properties": { "Description": "Wall CT, Friedhof Eythstr., Eythst.", "isHandicappedAccessible": 1 }, "geometry": { "type": "Point", "coordinates": [ 13.366474159849799, 52.459607642313003 ] } },
{ "type": "Feature", "properties": { "Description": "Wall CT, Weberwiese, Marchlewskistr.", "isHandicappedAccessible": 1 }, "geometry": { "type": "Point", "coordinates": [ 13.442779305251101, 52.516093495320803 ] } },
{ "type": "Feature", "properties": { "Description": "Wall CT, Simplonstr.", "isHandicappedAccessible": 1 }, "geometry": { "type": "Point", "coordinates": [ 13.4655841638968, 52.5045811099071 ] } },
{ "type": "Feature", "properties": { "Description": "Wall CT, Besselpark, Besselstr.", "isHandicappedAccessible": 1 }, "geometry": { "type": "Point", "coordinates": [ 13.391282801748, 52.504114293501601 ] } },
{ "type": "Feature", "properties": { "Description": "Toilette Rüdesheimer Str.", "isHandicappedAccessible": 0 }, "geometry": { "type": "Point", "coordinates": [ 13.314755, 52.473363 ] } },
{ "type": "Feature", "properties": { "Description": "Toilette Leuthener Str.", "isHandicappedAccessible": 0 }, "geometry": { "type": "Point", "coordinates": [ 13.363288, 52.481146 ] } },
{ "type": "Feature", "properties": { "Description": "Toilette Bulgarische Str.", "isHandicappedAccessible": 0 }, "geometry": { "type": "Point", "coordinates": [ 13.4800560474389, 52.485518722892401 ] } },
{ "type": "Feature", "properties": { "Description": "Toilette  ", "isHandicappedAccessible": 0 }, "geometry": { "type": "Point", "coordinates": [ 13.463345885275899, 52.4934218571887 ] } },
{ "type": "Feature", "properties": { "Description": "Wall CT, Pestalozzistr.", "isHandicappedAccessible": 1 }, "geometry": { "type": "Point", "coordinates": [ 13.306683, 52.5078805 ] } },
{ "type": "Feature", "properties": { "Description": "Wall CT, Preußenallee", "isHandicappedAccessible": 1 }, "geometry": { "type": "Point", "coordinates": [ 13.2600713030757, 52.516060701584301 ] } },
{ "type": "Feature", "properties": { "Description": "Wall CT, Hochmeisterplatz, Westfälische Str.", "isHandicappedAccessible": 1 }, "geometry": { "type": "Point", "coordinates": [ 13.299398655350799, 52.495341267272799 ] } },
{ "type": "Feature", "properties": { "Description": "Wall CT, Humboldthain, Gustav-Meyer-Allee", "isHandicappedAccessible": 1 }, "geometry": { "type": "Point", "coordinates": [ 13.390513411044701, 52.544748368837297 ] } },
{ "type": "Feature", "properties": { "Description": "Wall CT, Charlottenstr.", "isHandicappedAccessible": 1 }, "geometry": { "type": "Point", "coordinates": [ 13.3915, 52.514166666666704 ] } },
{ "type": "Feature", "properties": { "Description": "Wall CT, Alt-Moabit", "isHandicappedAccessible": 1 }, "geometry": { "type": "Point", "coordinates": [ 13.335501604332601, 52.524995954597202 ] } },
{ "type": "Feature", "properties": { "Description": "Wall CT, Buddeplatz (S-Bhf. Tegel), Buddestr.", "isHandicappedAccessible": 1 }, "geometry": { "type": "Point", "coordinates": [ 13.288545966355599, 52.5881948888971 ] } },
{ "type": "Feature", "properties": { "Description": "Wall CT, Göschenplatz, Oranienburger Str.", "isHandicappedAccessible": 1 }, "geometry": { "type": "Point", "coordinates": [ 13.332336232087499, 52.597545080160103 ] } },
{ "type": "Feature", "properties": { "Description": "Wall CT, Am Märchenbrunnen, Friedenstr.", "isHandicappedAccessible": 1 }, "geometry": { "type": "Point", "coordinates": [ 13.4273933717382, 52.527115646364699 ] } },
{ "type": "Feature", "properties": { "Description": "Wall CT, Forckenbeckplatz, Eldenaer Str.", "isHandicappedAccessible": 1 }, "geometry": { "type": "Point", "coordinates": [ 13.4610899385872, 52.519955350488303 ] } },
{ "type": "Feature", "properties": { "Description": "Wall CT, Degnerstr.", "isHandicappedAccessible": 1 }, "geometry": { "type": "Point", "coordinates": [ 13.4942620699196, 52.545595820013901 ] } },
{ "type": "Feature", "properties": { "Description": "Wall CT, Gürtelstr.", "isHandicappedAccessible": 1 }, "geometry": { "type": "Point", "coordinates": [ 13.476976179123801, 52.513146611285698 ] } },
{ "type": "Feature", "properties": { "Description": "Wall CT, Kladower Damm", "isHandicappedAccessible": 1 }, "geometry": { "type": "Point", "coordinates": [ 13.143970687910601, 52.453837887321001 ] } },
{ "type": "Feature", "properties": { "Description": "Wall CT, Hellersdorfer Str.", "isHandicappedAccessible": 1 }, "geometry": { "type": "Point", "coordinates": [ 13.5884471023787, 52.520867243558698 ] } },
{ "type": "Feature", "properties": { "Description": "Wall CT, Ahrensfelder Platz", "isHandicappedAccessible": 1 }, "geometry": { "type": "Point", "coordinates": [ 13.5658355425444, 52.570099369298198 ] } },
{ "type": "Feature", "properties": { "Description": "Wall CT, Lipschitzplatz", "isHandicappedAccessible": 1 }, "geometry": { "type": "Point", "coordinates": [ 13.463016651627701, 52.4245673848134 ] } },
{ "type": "Feature", "properties": { "Description": "Wall CT, Richardplatz", "isHandicappedAccessible": 1 }, "geometry": { "type": "Point", "coordinates": [ 13.4453848820056, 52.474071898772102 ] } },
{ "type": "Feature", "properties": { "Description": "Wall CT, Kollwitzplatz, Kollwitzstr.", "isHandicappedAccessible": 1 }, "geometry": { "type": "Point", "coordinates": [ 13.4170250013635, 52.535583350687702 ] } },
{ "type": "Feature", "properties": { "Description": "Wall CT, Elsa-Brändström-Str.", "isHandicappedAccessible": 1 }, "geometry": { "type": "Point", "coordinates": [ 13.413595519014599, 52.559918828094197 ] } },
{ "type": "Feature", "properties": { "Description": "Wall CT, Alt-Mariendorf", "isHandicappedAccessible": 1 }, "geometry": { "type": "Point", "coordinates": [ 13.387912180865801, 52.440158734936396 ] } },
{ "type": "Feature", "properties": { "Description": "Wall CT, Hauptstr.", "isHandicappedAccessible": 1 }, "geometry": { "type": "Point", "coordinates": [ 13.3528118756615, 52.484325156450097 ] } },
{ "type": "Feature", "properties": { "Description": "Wall CT, Argentinische Allee", "isHandicappedAccessible": 1 }, "geometry": { "type": "Point", "coordinates": [ 13.2401710897821, 52.442342871678697 ] } },
{ "type": "Feature", "properties": { "Description": "Wall CT, S-Bhf. Zehlendorf, Teltower Damm", "isHandicappedAccessible": 1 }, "geometry": { "type": "Point", "coordinates": [ 13.259624258479599, 52.431042951659599 ] } },
{ "type": "Feature", "properties": { "Description": "Wall CT, Brauerstr.", "isHandicappedAccessible": 1 }, "geometry": { "type": "Point", "coordinates": [ 13.326157, 52.427696 ] } },
{ "type": "Feature", "properties": { "Description": "Wall CT, S-Bhf. Grünau, Wassersportallee", "isHandicappedAccessible": 1 }, "geometry": { "type": "Point", "coordinates": [ 13.574246, 52.413678 ] } },
{ "type": "Feature", "properties": { "Description": "Wall CT, Sterndamm", "isHandicappedAccessible": 1 }, "geometry": { "type": "Point", "coordinates": [ 13.5093299795072, 52.453705676573897 ] } },
{ "type": "Feature", "properties": { "Description": "Wall CT, S-Bhf. Köpenick, Stellingdamm", "isHandicappedAccessible": 1 }, "geometry": { "type": "Point", "coordinates": [ 13.5802191173496, 52.4588468714187 ] } },
{ "type": "Feature", "properties": { "Description": "Wall CT, Kiefholzstr.", "isHandicappedAccessible": 1 }, "geometry": { "type": "Point", "coordinates": [ 13.486805364417901, 52.465891172731098 ] } },
{ "type": "Feature", "properties": { "Description": "Wall CT, Plesser Str.", "isHandicappedAccessible": 1 }, "geometry": { "type": "Point", "coordinates": [ 13.4511497884872, 52.4890646412465 ] } },
{ "type": "Feature", "properties": { "Description": "Wall CT, Schivelbeiner Str.", "isHandicappedAccessible": 1 }, "geometry": { "type": "Point", "coordinates": [ 13.41343229, 52.55067675 ] } },
{ "type": "Feature", "properties": { "Description": "Wall CT, Bornholmer Str.", "isHandicappedAccessible": 1 }, "geometry": { "type": "Point", "coordinates": [ 13.41329416, 52.55375525 ] } },
{ "type": "Feature", "properties": { "Description": "Wall CT, Steglitzer Damm", "isHandicappedAccessible": 1 }, "geometry": { "type": "Point", "coordinates": [ 13.3362051601007, 52.451008507060699 ] } },
{ "type": "Feature", "properties": { "Description": "Wall CT, Leonorenstr.", "isHandicappedAccessible": 1 }, "geometry": { "type": "Point", "coordinates": [ 13.343115236914199, 52.438957639789201 ] } },
{ "type": "Feature", "properties": { "Description": "Wall CT, Platz der Luftbrücke, Tempelhofer Damm", "isHandicappedAccessible": 1 }, "geometry": { "type": "Point", "coordinates": [ 13.385574465259101, 52.484589123808902 ] } },
{ "type": "Feature", "properties": { "Description": "Wall CT, Kurt-Schumacher-Platz, Scharnweberstr.", "isHandicappedAccessible": 1 }, "geometry": { "type": "Point", "coordinates": [ 13.3267155793166, 52.563919587881799 ] } },
{ "type": "Feature", "properties": { "Description": "Wall CT, Gudrunstr.", "isHandicappedAccessible": 1 }, "geometry": { "type": "Point", "coordinates": [ 13.50882, 52.51505 ] } },
{ "type": "Feature", "properties": { "Description": "Wall CT, Urbanstr.", "isHandicappedAccessible": 1 }, "geometry": { "type": "Point", "coordinates": [ 13.4085578538851, 52.492862992913999 ] } },
{ "type": "Feature", "properties": { "Description": "Wall CT, Planufer", "isHandicappedAccessible": 1 }, "geometry": { "type": "Point", "coordinates": [ 13.419832033300001, 52.495670256247401 ] } },
{ "type": "Feature", "properties": { "Description": "Wall CT, Gneisenaustr.", "isHandicappedAccessible": 1 }, "geometry": { "type": "Point", "coordinates": [ 13.398054, 52.490534 ] } },
{ "type": "Feature", "properties": { "Description": "Wall CT, Görlitzer Park, Wiener Str.", "isHandicappedAccessible": 1 }, "geometry": { "type": "Point", "coordinates": [ 13.4391568914807, 52.495058065683203 ] } },
{ "type": "Feature", "properties": { "Description": "Wall CT, Platz der Vereinten Nationen, Landsberger Allee", "isHandicappedAccessible": 1 }, "geometry": { "type": "Point", "coordinates": [ 13.4329856332671, 52.5235085677499 ] } },
{ "type": "Feature", "properties": { "Description": "Wall CT, Platz der Vereinten Nationen, Landsberger Allee", "isHandicappedAccessible": 1 }, "geometry": { "type": "Point", "coordinates": [ 13.4329856332671, 52.5235085677499 ] } },
{ "type": "Feature", "properties": { "Description": "Wall CT, Erich-Steinfurth-Str.", "isHandicappedAccessible": 1 }, "geometry": { "type": "Point", "coordinates": [ 13.4345572862, 52.511477365399998 ] } },
{ "type": "Feature", "properties": { "Description": "Wall CT, Warschauer Str.", "isHandicappedAccessible": 1 }, "geometry": { "type": "Point", "coordinates": [ 13.4506315673, 52.507619742199999 ] } },
{ "type": "Feature", "properties": { "Description": "Wall CT, Wühlischplatz, Wühlischstr.", "isHandicappedAccessible": 1 }, "geometry": { "type": "Point", "coordinates": [ 13.4639155114, 52.507900037299997 ] } },
{ "type": "Feature", "properties": { "Description": "Wall CT, Grellstr.", "isHandicappedAccessible": 1 }, "geometry": { "type": "Point", "coordinates": [ 13.438222675574099, 52.541483223138698 ] } },
{ "type": "Feature", "properties": { "Description": "Wall CT, Bülowstr.", "isHandicappedAccessible": 1 }, "geometry": { "type": "Point", "coordinates": [ 13.3670488964783, 52.493847646713 ] } },
{ "type": "Feature", "properties": { "Description": "Wall CT, Reinickendorfer Str.", "isHandicappedAccessible": 1 }, "geometry": { "type": "Point", "coordinates": [ 13.3699104981192, 52.541611140917098 ] } },
{ "type": "Feature", "properties": { "Description": "Wall CT, Osloer Str.", "isHandicappedAccessible": 1 }, "geometry": { "type": "Point", "coordinates": [ 13.3835024370767, 52.5560688305534 ] } },
{ "type": "Feature", "properties": { "Description": "Wall CT, Köllnischer Park, Rungestr.", "isHandicappedAccessible": 1 }, "geometry": { "type": "Point", "coordinates": [ 13.413572565667, 52.5127077113696 ] } },
{ "type": "Feature", "properties": { "Description": "Wall CT, Dürerplatz", "isHandicappedAccessible": 1 }, "geometry": { "type": "Point", "coordinates": [ 13.341501633828701, 52.469543411447098 ] } },
{ "type": "Feature", "properties": { "Description": "Wall CT, Priesterweg", "isHandicappedAccessible": 1 }, "geometry": { "type": "Point", "coordinates": [ 13.355711, 52.459251 ] } },
{ "type": "Feature", "properties": { "Description": "Wall CT, Marienfelder Allee", "isHandicappedAccessible": 1 }, "geometry": { "type": "Point", "coordinates": [ 13.3631543938859, 52.4134984395888 ] } },
{ "type": "Feature", "properties": { "Description": "Wall CT, Friedrichstr.", "isHandicappedAccessible": 1 }, "geometry": { "type": "Point", "coordinates": [ 13.391234, 52.501269 ] } },
{ "type": "Feature", "properties": { "Description": "Wall CT, Im Domstift", "isHandicappedAccessible": 1 }, "geometry": { "type": "Point", "coordinates": [ 13.4101617301817, 52.387778777986298 ] } },
{ "type": "Feature", "properties": { "Description": "Wall CT, Nöldnerplatz, Archibaldweg", "isHandicappedAccessible": 1 }, "geometry": { "type": "Point", "coordinates": [ 13.48398, 52.50302 ] } },
{ "type": "Feature", "properties": { "Description": "Wall CT, Marzahner Promenade (Fußgängerzone)", "isHandicappedAccessible": 1 }, "geometry": { "type": "Point", "coordinates": [ 13.549245, 52.544367 ] } },
{ "type": "Feature", "properties": { "Description": "Wall CT, Waldstr.", "isHandicappedAccessible": 1 }, "geometry": { "type": "Point", "coordinates": [ 13.3306064855452, 52.5274148885999 ] } },
{ "type": "Feature", "properties": { "Description": "Wall CT, Hugenottenplatz, Schweizer Tal", "isHandicappedAccessible": 1 }, "geometry": { "type": "Point", "coordinates": [ 13.4205648128286, 52.607144526446803 ] } },
{ "type": "Feature", "properties": { "Description": "Wall CT, Hohenzollerndamm", "isHandicappedAccessible": 1 }, "geometry": { "type": "Point", "coordinates": [ 13.2818898456133, 52.476678826701402 ] } },
{ "type": "Feature", "properties": { "Description": "Wall CT, Wilhelminenhofstr.", "isHandicappedAccessible": 1 }, "geometry": { "type": "Point", "coordinates": [ 13.5266717549591, 52.458592859443499 ] } },
{ "type": "Feature", "properties": { "Description": "Wall CT, Bundesallee, Friedrich-Wilhelm-Platz", "isHandicappedAccessible": 1 }, "geometry": { "type": "Point", "coordinates": [ 13.3279901054745, 52.472596315685898 ] } },
{ "type": "Feature", "properties": { "Description": "Wall CT, Achillesstr.", "isHandicappedAccessible": 1 }, "geometry": { "type": "Point", "coordinates": [ 13.48851, 52.617635 ] } },
{ "type": "Feature", "properties": { "Description": "Wall CT, S-Bhf. Wilhelmshagen, Schönblicker Str.", "isHandicappedAccessible": 1 }, "geometry": { "type": "Point", "coordinates": [ 13.721004641574501, 52.439081737872598 ] } },
{ "type": "Feature", "properties": { "Description": "Wall CT, Badensche Str.", "isHandicappedAccessible": 1 }, "geometry": { "type": "Point", "coordinates": [ 13.3274845332077, 52.486476948756597 ] } },
{ "type": "Feature", "properties": { "Description": "Wall CT, Eberbacher Str.", "isHandicappedAccessible": 1 }, "geometry": { "type": "Point", "coordinates": [ 13.3092685301689, 52.473324575463003 ] } },
{ "type": "Feature", "properties": { "Description": "Wall CT, Weitlingstr.", "isHandicappedAccessible": 1 }, "geometry": { "type": "Point", "coordinates": [ 13.4993596999717, 52.510631876939499 ] } },
{ "type": "Feature", "properties": { "Description": "Wall CT, Seddiner Str.", "isHandicappedAccessible": 1 }, "geometry": { "type": "Point", "coordinates": [ 13.520834145912801, 52.513501905000098 ] } },
{ "type": "Feature", "properties": { "Description": "Toilette Grünberger Str.", "isHandicappedAccessible": 1 }, "geometry": { "type": "Point", "coordinates": [ 13.4606556296341, 52.510697156664698 ] } },
{ "type": "Feature", "properties": { "Description": "Wall CT, Breitenbachplatz", "isHandicappedAccessible": 1 }, "geometry": { "type": "Point", "coordinates": [ 13.308664823021701, 52.467236789522701 ] } },
{ "type": "Feature", "properties": { "Description": "Wall CT, Griechische Allee", "isHandicappedAccessible": 1 }, "geometry": { "type": "Point", "coordinates": [ 13.5138909063174, 52.464637078648202 ] } },
{ "type": "Feature", "properties": { "Description": "Wall CT, Hempelsteig", "isHandicappedAccessible": 1 }, "geometry": { "type": "Point", "coordinates": [ 13.240857, 52.525505 ] } },
{ "type": "Feature", "properties": { "Description": "Wall CT, Goerzallee", "isHandicappedAccessible": 1 }, "geometry": { "type": "Point", "coordinates": [ 13.3093156903864, 52.4309018915121 ] } },
{ "type": "Feature", "properties": { "Description": "Wall CT, Munsterdamm", "isHandicappedAccessible": 1 }, "geometry": { "type": "Point", "coordinates": [ 13.3491057199504, 52.458553061293898 ] } },
{ "type": "Feature", "properties": { "Description": "Wall CT, Ostpreußendamm", "isHandicappedAccessible": 1 }, "geometry": { "type": "Point", "coordinates": [ 13.304900271348799, 52.417633923766502 ] } },
{ "type": "Feature", "properties": { "Description": "Wall CT, Zingster Str.", "isHandicappedAccessible": 1 }, "geometry": { "type": "Point", "coordinates": [ 13.496949550347299, 52.569873918080702 ] } },
{ "type": "Feature", "properties": { "Description": "Wall CT, Am Heidefriedhof, Reißeckstr.", "isHandicappedAccessible": 1 }, "geometry": { "type": "Point", "coordinates": [ 13.392099276704601, 52.439752311965897 ] } },
{ "type": "Feature", "properties": { "Description": "Wall CT, Steglitzer Damm", "isHandicappedAccessible": 1 }, "geometry": { "type": "Point", "coordinates": [ 13.3428182601929, 52.45068359375 ] } },
{ "type": "Feature", "properties": { "Description": "Wall CT, Schloßstr.", "isHandicappedAccessible": 1 }, "geometry": { "type": "Point", "coordinates": [ 13.3214325154, 52.457269514 ] } },
{ "type": "Feature", "properties": { "Description": "Wall CT, S-Bhf. Wartenberg , Egon-Erwin-Kisch-Str.", "isHandicappedAccessible": 1 }, "geometry": { "type": "Point", "coordinates": [ 13.5046711288011, 52.573330103348603 ] } },
{ "type": "Feature", "properties": { "Description": "Wall CT, Landsberger Allee", "isHandicappedAccessible": 1 }, "geometry": { "type": "Point", "coordinates": [ 13.470695020300001, 52.531008210700001 ] } },
{ "type": "Feature", "properties": { "Description": "Wall CT, S-Bhf. Karlshorst, Stolzenfelsstr.", "isHandicappedAccessible": 1 }, "geometry": { "type": "Point", "coordinates": [ 13.5260174309, 52.4813251482 ] } },
{ "type": "Feature", "properties": { "Description": "Toilette Bernauer Str. (DLRG-Rettungsstelle/Badestelle/Fähre) (ex. Bernauer Str. an der Badestelle (Reiswerder))", "isHandicappedAccessible": 0 }, "geometry": { "type": "Point", "coordinates": [ 13.2565555555556, 52.568138888888903 ] } },
{ "type": "Feature", "properties": { "Description": "Wall CT, Boulevard Kastanienallee", "isHandicappedAccessible": 1 }, "geometry": { "type": "Point", "coordinates": [ 13.603352313404599, 52.531912050002902 ] } },
{ "type": "Feature", "properties": { "Description": "Wall CT, Attilaplatz, Attilastr.", "isHandicappedAccessible": 1 }, "geometry": { "type": "Point", "coordinates": [ 13.3759973597359, 52.455911390208797 ] } },
{ "type": "Feature", "properties": { "Description": "Wall CT, Hranitzkistr.", "isHandicappedAccessible": 1 }, "geometry": { "type": "Point", "coordinates": [ 13.3710977471902, 52.422519840207698 ] } },
{ "type": "Feature", "properties": { "Description": "Wall CT, Spittelmarkt, Niederwallstr.", "isHandicappedAccessible": 1 }, "geometry": { "type": "Point", "coordinates": [ 13.4007839020002, 52.5116668951405 ] } },
{ "type": "Feature", "properties": { "Description": "Wall CT, Hermannplatz", "isHandicappedAccessible": 1 }, "geometry": { "type": "Point", "coordinates": [ 13.425297989900001, 52.487631504900001 ] } },
{ "type": "Feature", "properties": { "Description": "Wall CT, Antonplatz, Berliner Allee", "isHandicappedAccessible": 1 }, "geometry": { "type": "Point", "coordinates": [ 13.451236714791399, 52.548166004695197 ] } },
{ "type": "Feature", "properties": { "Description": "Wall CT, S-Bhf. Frohnau, Welfenallee", "isHandicappedAccessible": 1 }, "geometry": { "type": "Point", "coordinates": [ 13.2890079265, 52.631985803900001 ] } },
{ "type": "Feature", "properties": { "Description": "Wall CT, Rudower Chaussee", "isHandicappedAccessible": 1 }, "geometry": { "type": "Point", "coordinates": [ 13.53926, 52.43443 ] } },
{ "type": "Feature", "properties": { "Description": "Wall CT, Neuendorfer Str.", "isHandicappedAccessible": 1 }, "geometry": { "type": "Point", "coordinates": [ 13.2056353123, 52.541433992100004 ] } },
{ "type": "Feature", "properties": { "Description": "Wall CT, Hohenzollernplatz, Hohenzollerndamm", "isHandicappedAccessible": 1 }, "geometry": { "type": "Point", "coordinates": [ 13.3250563841, 52.494013819 ] } },
{ "type": "Feature", "properties": { "Description": "Wall CT, S-Bhf. Biesdorf, Wuhlgartenweg", "isHandicappedAccessible": 1 }, "geometry": { "type": "Point", "coordinates": [ 13.5549178147, 52.513420205800003 ] } },
{ "type": "Feature", "properties": { "Description": "Wall CT, Innsbrucker Platz", "isHandicappedAccessible": 1 }, "geometry": { "type": "Point", "coordinates": [ 13.3434712846, 52.478675575799997 ] } },
{ "type": "Feature", "properties": { "Description": "Wall CT, Wernsdorfer Str.", "isHandicappedAccessible": 1 }, "geometry": { "type": "Point", "coordinates": [ 13.6493298625, 52.375817002700003 ] } },
{ "type": "Feature", "properties": { "Description": "Wall CT, Winterfeldtplatz, Hohenstaufenstr.", "isHandicappedAccessible": 1 }, "geometry": { "type": "Point", "coordinates": [ 13.3536221927, 52.4948779984 ] } },
{ "type": "Feature", "properties": { "Description": "Wall CT, George-Grosz-Platz, Kurfürstendamm", "isHandicappedAccessible": 1 }, "geometry": { "type": "Point", "coordinates": [ 13.31733472, 52.501480690199998 ] } },
{ "type": "Feature", "properties": { "Description": "Wall CT, Waldstr.", "isHandicappedAccessible": 1 }, "geometry": { "type": "Point", "coordinates": [ 13.4002351085133, 52.580673166829698 ] } },
{ "type": "Feature", "properties": { "Description": "Wall CT, Fontanestr.", "isHandicappedAccessible": 1 }, "geometry": { "type": "Point", "coordinates": [ 13.263703, 52.487504 ] } },
{ "type": "Feature", "properties": { "Description": "Wall CT, S+U-Bhf. Wuhletal, Altentreptower Str.", "isHandicappedAccessible": 1 }, "geometry": { "type": "Point", "coordinates": [ 13.5748868504834, 52.512900739965097 ] } },
{ "type": "Feature", "properties": { "Description": "Wall CT, U-Bhf. Kienberg, Neue Grottkauer Str.", "isHandicappedAccessible": 1 }, "geometry": { "type": "Point", "coordinates": [ 13.591577839657001, 52.5294186207121 ] } },
{ "type": "Feature", "properties": { "Description": "Wall CT, Quedlinburger Str.", "isHandicappedAccessible": 1 }, "geometry": { "type": "Point", "coordinates": [ 13.604701825299999, 52.539385473099998 ] } },
{ "type": "Feature", "properties": { "Description": "Wall CT, Hellersdorfer Str.", "isHandicappedAccessible": 1 }, "geometry": { "type": "Point", "coordinates": [ 13.6010719319, 52.535818959399997 ] } },
{ "type": "Feature", "properties": { "Description": "Wall CT, Roedernstr.", "isHandicappedAccessible": 1 }, "geometry": { "type": "Point", "coordinates": [ 13.601172456800001, 52.482551791600002 ] } },
{ "type": "Feature", "properties": { "Description": "Wall CT, Elsterwerdaer Platz", "isHandicappedAccessible": 1 }, "geometry": { "type": "Point", "coordinates": [ 13.5609083175659, 52.505939483642599 ] } },
{ "type": "Feature", "properties": { "Description": "Wall CT, Helene-Weigel-Platz", "isHandicappedAccessible": 1 }, "geometry": { "type": "Point", "coordinates": [ 13.5380301295883, 52.527968388973598 ] } },
{ "type": "Feature", "properties": { "Description": "Wall CT, Debenzer Str.", "isHandicappedAccessible": 1 }, "geometry": { "type": "Point", "coordinates": [ 13.54735, 52.500953 ] } },
{ "type": "Feature", "properties": { "Description": "Wall CT, Rathaus Spandau, Altstädter Ring", "isHandicappedAccessible": 1 }, "geometry": { "type": "Point", "coordinates": [ 13.200429060080101, 52.535470082299803 ] } },
{ "type": "Feature", "properties": { "Description": "Wall CT, Imchenplatz, Imchenallee", "isHandicappedAccessible": 1 }, "geometry": { "type": "Point", "coordinates": [ 13.1489187460324, 52.452524998659499 ] } },
{ "type": "Feature", "properties": { "Description": "Wall CT, Metzer Platz", "isHandicappedAccessible": 1 }, "geometry": { "type": "Point", "coordinates": [ 13.196921236571599, 52.525156785774897 ] } },
{ "type": "Feature", "properties": { "Description": "Wall CT, Moritzstr.", "isHandicappedAccessible": 1 }, "geometry": { "type": "Point", "coordinates": [ 13.2011111111111, 52.538333333333298 ] } },
{ "type": "Feature", "properties": { "Description": "Wall CT, Wiltbergstr.", "isHandicappedAccessible": 1 }, "geometry": { "type": "Point", "coordinates": [ 13.494606453114001, 52.635655578521302 ] } },
{ "type": "Feature", "properties": { "Description": "Wall CT, Breite Str.", "isHandicappedAccessible": 1 }, "geometry": { "type": "Point", "coordinates": [ 13.407346527823099, 52.5702539545699 ] } },
{ "type": "Feature", "properties": { "Description": "Wall CT, Berliner Allee", "isHandicappedAccessible": 1 }, "geometry": { "type": "Point", "coordinates": [ 13.466255563858599, 52.552614850170499 ] } },
{ "type": "Feature", "properties": { "Description": "Wall CT, Schönhauser Allee", "isHandicappedAccessible": 1 }, "geometry": { "type": "Point", "coordinates": [ 13.411940574646, 52.543052673339801 ] } },
{ "type": "Feature", "properties": { "Description": "Wall CT, Wichertstr.", "isHandicappedAccessible": 1 }, "geometry": { "type": "Point", "coordinates": [ 13.42089017, 52.54864128 ] } },
{ "type": "Feature", "properties": { "Description": "Wall CT, Wichertstr.", "isHandicappedAccessible": 1 }, "geometry": { "type": "Point", "coordinates": [ 13.42732495, 52.545866980100001 ] } },
{ "type": "Feature", "properties": { "Description": "Wall CT, Helmholtzplatz, Raumerstr.", "isHandicappedAccessible": 1 }, "geometry": { "type": "Point", "coordinates": [ 13.418659760580701, 52.542899739346801 ] } },
{ "type": "Feature", "properties": { "Description": "Wall CT, Am Falkplatz", "isHandicappedAccessible": 1 }, "geometry": { "type": "Point", "coordinates": [ 13.4054260825, 52.546765034899998 ] } },
{ "type": "Feature", "properties": { "Description": "Wall CT, Arnswalder Platz, Bötzowstr.", "isHandicappedAccessible": 1 }, "geometry": { "type": "Point", "coordinates": [ 13.4371079873968, 52.533595290310302 ] } },
{ "type": "Feature", "properties": { "Description": "Wall CT, Am Weißen See, Parkstr.", "isHandicappedAccessible": 1 }, "geometry": { "type": "Point", "coordinates": [ 13.4587438498199, 52.555574389131799 ] } },
{ "type": "Feature", "properties": { "Description": "Wall CT, Schillerpromenade", "isHandicappedAccessible": 1 }, "geometry": { "type": "Point", "coordinates": [ 13.421999247131501, 52.4775845145735 ] } },
{ "type": "Feature", "properties": { "Description": "Wall CT, Sonnenallee", "isHandicappedAccessible": 1 }, "geometry": { "type": "Point", "coordinates": [ 13.464290658835999, 52.470296368347199 ] } },
{ "type": "Feature", "properties": { "Description": "Wall CT, Boddinplatz, Mainzer Str.", "isHandicappedAccessible": 1 }, "geometry": { "type": "Point", "coordinates": [ 13.4284121007425, 52.479913348962903 ] } },
{ "type": "Feature", "properties": { "Description": "Wall CT, Seestr.", "isHandicappedAccessible": 1 }, "geometry": { "type": "Point", "coordinates": [ 13.3515952183918, 52.5503828539617 ] } },
{ "type": "Feature", "properties": { "Description": "Wall CT, Savignyplatz", "isHandicappedAccessible": 1 }, "geometry": { "type": "Point", "coordinates": [ 13.322725, 52.505252 ] } },
{ "type": "Feature", "properties": { "Description": "Wall CT, Schönefelder Chaussee", "isHandicappedAccessible": 1 }, "geometry": { "type": "Point", "coordinates": [ 13.5275184661, 52.4109872979 ] } },
{ "type": "Feature", "properties": { "Description": "Wall CT, Briesingstr.", "isHandicappedAccessible": 1 }, "geometry": { "type": "Point", "coordinates": [ 13.398498662364901, 52.386517851077699 ] } },
{ "type": "Feature", "properties": { "Description": "Wall CT, Kurt-Schumacher-Damm", "isHandicappedAccessible": 1 }, "geometry": { "type": "Point", "coordinates": [ 13.29402034, 52.53625419 ] } },
{ "type": "Feature", "properties": { "Description": "Wall CT, Bundesallee, Bundesplatz", "isHandicappedAccessible": 1 }, "geometry": { "type": "Point", "coordinates": [ 13.3282867070272, 52.479006960045602 ] } },
{ "type": "Feature", "properties": { "Description": "Wall CT, Fulhamer Allee", "isHandicappedAccessible": 1 }, "geometry": { "type": "Point", "coordinates": [ 13.440223823425599, 52.447710550296101 ] } },
{ "type": "Feature", "properties": { "Description": "Wall CT, Park am Weinbergsweg, Weinbergsweg", "isHandicappedAccessible": 1 }, "geometry": { "type": "Point", "coordinates": [ 13.4030886906136, 52.531947706568197 ] } },
{ "type": "Feature", "properties": { "Description": "Wall CT, Am Treptower Park", "isHandicappedAccessible": 1 }, "geometry": { "type": "Point", "coordinates": [ 13.464374587928001, 52.487466758391101 ] } },
{ "type": "Feature", "properties": { "Description": "Wall CT, S-Bhf. Friedrichshagen, Dahlwitzer Landstr.", "isHandicappedAccessible": 1 }, "geometry": { "type": "Point", "coordinates": [ 13.62535, 52.457726 ] } },
{ "type": "Feature", "properties": { "Description": "Wall CT, Comeniusplatz, Torellstr.", "isHandicappedAccessible": 1 }, "geometry": { "type": "Point", "coordinates": [ 13.447336160483299, 52.511446168810302 ] } },
{ "type": "Feature", "properties": { "Description": "Wall CT, Traveplatz, Weichselstr.", "isHandicappedAccessible": 1 }, "geometry": { "type": "Point", "coordinates": [ 13.469024276396199, 52.511231535322999 ] } },
{ "type": "Feature", "properties": { "Description": "Wall CT, Skalitzer Str.", "isHandicappedAccessible": 1 }, "geometry": { "type": "Point", "coordinates": [ 13.4303110155598, 52.499960236872703 ] } },
{ "type": "Feature", "properties": { "Description": "Wall CT, Alfred-Scholz-Platz, Richardstr.", "isHandicappedAccessible": 1 }, "geometry": { "type": "Point", "coordinates": [ 13.438141, 52.478802 ] } },
{ "type": "Feature", "properties": { "Description": "Wall CT, Ludwigkirchplatz", "isHandicappedAccessible": 1 }, "geometry": { "type": "Point", "coordinates": [ 13.3223900106436, 52.497141311651703 ] } },
{ "type": "Feature", "properties": { "Description": "Wall CT, Turmstr.", "isHandicappedAccessible": 1 }, "geometry": { "type": "Point", "coordinates": [ 13.348094965884499, 52.526093090525997 ] } },
{ "type": "Feature", "properties": { "Description": "Wall CT, Invalidenstr.", "isHandicappedAccessible": 1 }, "geometry": { "type": "Point", "coordinates": [ 13.3781628439159, 52.528957574527901 ] } },
{ "type": "Feature", "properties": { "Description": "Wall CT, Burgstr. (James-Simon-Park)", "isHandicappedAccessible": 1 }, "geometry": { "type": "Point", "coordinates": [ 13.400429357, 52.521999592 ] } },
{ "type": "Feature", "properties": { "Description": "Wall CT, Potsdamer Str.", "isHandicappedAccessible": 1 }, "geometry": { "type": "Point", "coordinates": [ 13.363061690807299, 52.499879052593698 ] } },
{ "type": "Feature", "properties": { "Description": "Wall CT, Museumsinsel, Am Lustgarten", "isHandicappedAccessible": 1 }, "geometry": { "type": "Point", "coordinates": [ 13.399898076099999, 52.519467325900003 ] } },
{ "type": "Feature", "properties": { "Description": "Wall CT, Str. des 17. Juni", "isHandicappedAccessible": 1 }, "geometry": { "type": "Point", "coordinates": [ 13.375539128749599, 52.516372017062402 ] } },
{ "type": "Feature", "properties": { "Description": "Wall CT, Linkstr.", "isHandicappedAccessible": 1 }, "geometry": { "type": "Point", "coordinates": [ 13.3742894166, 52.505570408600001 ] } },
{ "type": "Feature", "properties": { "Description": "Wall CT, Leopoldplatz, Müllerstr.", "isHandicappedAccessible": 1 }, "geometry": { "type": "Point", "coordinates": [ 13.3586066, 52.5470043 ] } },
{ "type": "Feature", "properties": { "Description": "Wall CT, Ungarnstr.", "isHandicappedAccessible": 1 }, "geometry": { "type": "Point", "coordinates": [ 13.35593646, 52.555437 ] } },
{ "type": "Feature", "properties": { "Description": "Wall CT, Alt-Tegel", "isHandicappedAccessible": 1 }, "geometry": { "type": "Point", "coordinates": [ 13.282788456362301, 52.589852773373302 ] } },
{ "type": "Feature", "properties": { "Description": "Wall CT, An der Werderlake", "isHandicappedAccessible": 1 }, "geometry": { "type": "Point", "coordinates": [ 13.5166011055646, 52.4200935571602 ] } },
{ "type": "Feature", "properties": { "Description": "Wall CT, S-Bhf. Plänterwald, Bahnhofsvorplatz", "isHandicappedAccessible": 1 }, "geometry": { "type": "Point", "coordinates": [ 13.4739695463681, 52.4787140672384 ] } },
{ "type": "Feature", "properties": { "Description": "Wall CT, Greenwichpromenade", "isHandicappedAccessible": 1 }, "geometry": { "type": "Point", "coordinates": [ 13.272597216399101, 52.5890975626873 ] } },
{ "type": "Feature", "properties": { "Description": "Wall CT, Wittenbergplatz, Ansbacher Str.", "isHandicappedAccessible": 1 }, "geometry": { "type": "Point", "coordinates": [ 13.3427270609067, 52.502467629182497 ] } },
{ "type": "Feature", "properties": { "Description": "Wall CT, Mariendorfer Damm", "isHandicappedAccessible": 1 }, "geometry": { "type": "Point", "coordinates": [ 13.3856663883506, 52.444383191740101 ] } },
{ "type": "Feature", "properties": { "Description": "Wall CT, S-u. U-Bhf. Tempelhof, Tempelhofer Damm", "isHandicappedAccessible": 1 }, "geometry": { "type": "Point", "coordinates": [ 13.385392, 52.470273 ] } },
{ "type": "Feature", "properties": { "Description": "Wall CT, Klausenerplatz", "isHandicappedAccessible": 1 }, "geometry": { "type": "Point", "coordinates": [ 13.290356505, 52.51879627 ] } },
{ "type": "Feature", "properties": { "Description": "Wall CT, Hans-Rosenthal-Platz , Kufsteiner Str.", "isHandicappedAccessible": 1 }, "geometry": { "type": "Point", "coordinates": [ 13.33693, 52.480497 ] } },
{ "type": "Feature", "properties": { "Description": "Wall CT, Trakehner Allee", "isHandicappedAccessible": 1 }, "geometry": { "type": "Point", "coordinates": [ 13.2434255789804, 52.512951358555 ] } },
{ "type": "Feature", "properties": { "Description": "Wall CT, Olympischer Platz", "isHandicappedAccessible": 1 }, "geometry": { "type": "Point", "coordinates": [ 13.2443537242179, 52.515597450523103 ] } },
{ "type": "Feature", "properties": { "Description": "Wall CT, Trakehner Allee", "isHandicappedAccessible": 1 }, "geometry": { "type": "Point", "coordinates": [ 13.240826986444, 52.512195648339798 ] } },
{ "type": "Feature", "properties": { "Description": "Wall CT, Jesse-Owens-Allee", "isHandicappedAccessible": 1 }, "geometry": { "type": "Point", "coordinates": [ 13.2368291260182, 52.510622852580603 ] } },
{ "type": "Feature", "properties": { "Description": "Wall CT, Siegfriedstr.", "isHandicappedAccessible": 1 }, "geometry": { "type": "Point", "coordinates": [ 13.4314583180754, 52.467862106557099 ] } },
{ "type": "Feature", "properties": { "Description": "Wall CT, Joachim-Gottschalk-Weg", "isHandicappedAccessible": 1 }, "geometry": { "type": "Point", "coordinates": [ 13.476612190236301, 52.422660213594597 ] } },
{ "type": "Feature", "properties": { "Description": "Wall CT, Hallesches Ufer", "isHandicappedAccessible": 1 }, "geometry": { "type": "Point", "coordinates": [ 13.391325704390299, 52.4979512797239 ] } },
{ "type": "Feature", "properties": { "Description": "Wall CT, Max.-Kraft-Platz, Katzlerstr.", "isHandicappedAccessible": 1 }, "geometry": { "type": "Point", "coordinates": [ 13.3690376999477, 52.492757952710498 ] } },
{ "type": "Feature", "properties": { "Description": "Wall CT, Büsingstr.", "isHandicappedAccessible": 1 }, "geometry": { "type": "Point", "coordinates": [ 13.3261596400353, 52.465685299762903 ] } },
{ "type": "Feature", "properties": { "Description": "Wall CT, Stübbenstr.", "isHandicappedAccessible": 1 }, "geometry": { "type": "Point", "coordinates": [ 13.3379572238377, 52.488485112192699 ] } },
{ "type": "Feature", "properties": { "Description": "Wall CT, Röblingstr.", "isHandicappedAccessible": 1 }, "geometry": { "type": "Point", "coordinates": [ 13.366536767590301, 52.449873599525198 ] } },
{ "type": "Feature", "properties": { "Description": "Wall CT, Dennewitzplatz, Dennewitzstr.", "isHandicappedAccessible": 1 }, "geometry": { "type": "Point", "coordinates": [ 13.3669367751199, 52.497154322588102 ] } },
{ "type": "Feature", "properties": { "Description": "Wall CT, Holzmannstr.", "isHandicappedAccessible": 1 }, "geometry": { "type": "Point", "coordinates": [ 13.418225262803499, 52.462518717394197 ] } },
{ "type": "Feature", "properties": { "Description": "Wall CT, Wartburgplatz, Martin-Luther-Str.", "isHandicappedAccessible": 1 }, "geometry": { "type": "Point", "coordinates": [ 13.3453017022547, 52.487954264495798 ] } },
{ "type": "Feature", "properties": { "Description": "Wall CT, Motzstr.", "isHandicappedAccessible": 1 }, "geometry": { "type": "Point", "coordinates": [ 13.345158579948, 52.496906823638298 ] } },
{ "type": "Feature", "properties": { "Description": "Wall CT, Waltersdorfer Chaussee", "isHandicappedAccessible": 1 }, "geometry": { "type": "Point", "coordinates": [ 13.497740316338501, 52.4158088417092 ] } },
{ "type": "Feature", "properties": { "Description": "Wall CT, Berkaer Str.", "isHandicappedAccessible": 1 }, "geometry": { "type": "Point", "coordinates": [ 13.2904180558149, 52.475751688829497 ] } },
{ "type": "Feature", "properties": { "Description": "Wall CT, Rudolfplatz, Modersohnstr.", "isHandicappedAccessible": 1 }, "geometry": { "type": "Point", "coordinates": [ 13.4568589044744, 52.502683072831402 ] } },
{ "type": "Feature", "properties": { "Description": "Wall CT, Falckensteinstr.", "isHandicappedAccessible": 1 }, "geometry": { "type": "Point", "coordinates": [ 13.443025428423301, 52.498992769797198 ] } },
{ "type": "Feature", "properties": { "Description": "Wall CT, Oranienplatz", "isHandicappedAccessible": 1 }, "geometry": { "type": "Point", "coordinates": [ 13.4151105784254, 52.5025964081577 ] } },
{ "type": "Feature", "properties": { "Description": "Wall CT, Mariannenplatz", "isHandicappedAccessible": 1 }, "geometry": { "type": "Point", "coordinates": [ 13.424531, 52.50307 ] } },
{ "type": "Feature", "properties": { "Description": "Wall CT, Klixarena, Zobeltitzstr.", "isHandicappedAccessible": 1 }, "geometry": { "type": "Point", "coordinates": [ 13.308729673772, 52.570240401001001 ] } },
{ "type": "Feature", "properties": { "Description": "Wall CT, Letteplatz, Letteallee", "isHandicappedAccessible": 1 }, "geometry": { "type": "Point", "coordinates": [ 13.370905042255499, 52.5632981645931 ] } },
{ "type": "Feature", "properties": { "Description": "Wall CT, Schäfersee, Am Schäfersee", "isHandicappedAccessible": 1 }, "geometry": { "type": "Point", "coordinates": [ 13.3586228154509, 52.563453016810698 ] } },
{ "type": "Feature", "properties": { "Description": "Wall CT, Auguste-Viktoria-Allee", "isHandicappedAccessible": 1 }, "geometry": { "type": "Point", "coordinates": [ 13.3238639955806, 52.570099357190202 ] } },
{ "type": "Feature", "properties": { "Description": "Wall CT, Senftenberger Ring", "isHandicappedAccessible": 1 }, "geometry": { "type": "Point", "coordinates": [ 13.353790066078, 52.599665175416199 ] } },
{ "type": "Feature", "properties": { "Description": "Wall CT, Böhmischer Platz, Böhmische Str.", "isHandicappedAccessible": 1 }, "geometry": { "type": "Point", "coordinates": [ 13.4493724241377, 52.473989183151197 ] } },
{ "type": "Feature", "properties": { "Description": "Wall CT, Bürgerpark Pankow, Leonhard-Frank-Str.", "isHandicappedAccessible": 1 }, "geometry": { "type": "Point", "coordinates": [ 13.388856030179801, 52.569524187374498 ] } },
{ "type": "Feature", "properties": { "Description": "Wall CT, Am Schlachtensee", "isHandicappedAccessible": 1 }, "geometry": { "type": "Point", "coordinates": [ 13.2144458755228, 52.440158474187598 ] } },
{ "type": "Feature", "properties": { "Description": "Wall CT, Mühlenstr.", "isHandicappedAccessible": 1 }, "geometry": { "type": "Point", "coordinates": [ 13.3477631316314, 52.432159727923498 ] } },
{ "type": "Feature", "properties": { "Description": "Wall CT, Osloer Str.", "isHandicappedAccessible": 1 }, "geometry": { "type": "Point", "coordinates": [ 13.372252196585301, 52.557039819952003 ] } },
{ "type": "Feature", "properties": { "Description": "Wall CT, Stralsunder Str. (Fußgängerzone)", "isHandicappedAccessible": 1 }, "geometry": { "type": "Point", "coordinates": [ 13.3952777777778, 52.5397777777778 ] } },
{ "type": "Feature", "properties": { "Description": "Wall CT, Weiskopffstr.", "isHandicappedAccessible": 1 }, "geometry": { "type": "Point", "coordinates": [ 13.5417987687468, 52.457776201881799 ] } },
{ "type": "Feature", "properties": { "Description": "Wall CT, Ottomar-Geschke-Str.", "isHandicappedAccessible": 1 }, "geometry": { "type": "Point", "coordinates": [ 13.5628400782931, 52.446494971675598 ] } },
{ "type": "Feature", "properties": { "Description": "Wall CT, S-Bhf. Mahlsdorf, Hönower Str.", "isHandicappedAccessible": 1 }, "geometry": { "type": "Point", "coordinates": [ 13.612438996623601, 52.511916127972498 ] } },
{ "type": "Feature", "properties": { "Description": "Wall CT, Thomashöhe, Thomasstr.", "isHandicappedAccessible": 1 }, "geometry": { "type": "Point", "coordinates": [ 13.438905760934, 52.473714141246298 ] } },
{ "type": "Feature", "properties": { "Description": "Wall CT, Weichselstr. ", "isHandicappedAccessible": 1 }, "geometry": { "type": "Point", "coordinates": [ 13.439041275332, 52.488860233472899 ] } },
{ "type": "Feature", "properties": { "Description": "Wall CT, Prerower Platz, Zingster Str.", "isHandicappedAccessible": 1 }, "geometry": { "type": "Point", "coordinates": [ 13.504097989772999, 52.564428799493299 ] } },
{ "type": "Feature", "properties": { "Description": "Wall CT, Vincent-van-Gogh-Str.", "isHandicappedAccessible": 1 }, "geometry": { "type": "Point", "coordinates": [ 13.5244707000485, 52.564692682344997 ] } },
{ "type": "Feature", "properties": { "Description": "Wall CT, Storkower Str.", "isHandicappedAccessible": 1 }, "geometry": { "type": "Point", "coordinates": [ 13.4655294418335, 52.5243949890137 ] } },
{ "type": "Feature", "properties": { "Description": "Wall CT, Hauptstr.", "isHandicappedAccessible": 1 }, "geometry": { "type": "Point", "coordinates": [ 13.505292921455901, 52.548651661190398 ] } },
{ "type": "Feature", "properties": { "Description": "Wall CT, Am Tierpark", "isHandicappedAccessible": 1 }, "geometry": { "type": "Point", "coordinates": [ 13.5227291739323, 52.497458385664302 ] } },
{ "type": "Feature", "properties": { "Description": "Wall CT, Rheinsteinpark, Königswinterstr.", "isHandicappedAccessible": 1 }, "geometry": { "type": "Point", "coordinates": [ 13.529794866432299, 52.483268953068098 ] } },
{ "type": "Feature", "properties": { "Description": "Wall CT, Paul-Lincke-Ufer", "isHandicappedAccessible": 1 }, "geometry": { "type": "Point", "coordinates": [ 13.4318183693879, 52.492845991969297 ] } },
{ "type": "Feature", "properties": { "Description": "Wall CT, Waterloo-Ufer", "isHandicappedAccessible": 1 }, "geometry": { "type": "Point", "coordinates": [ 13.3930303824613, 52.497389835645102 ] } },
{ "type": "Feature", "properties": { "Description": "Wall CT, Steinbergpark, Waidmannsluster Damm", "isHandicappedAccessible": 1 }, "geometry": { "type": "Point", "coordinates": [ 13.305976732399801, 52.601797680947598 ] } },
{ "type": "Feature", "properties": { "Description": "Wall CT, Bhf. Jungfernheide, Lambertstr.", "isHandicappedAccessible": 1 }, "geometry": { "type": "Point", "coordinates": [ 13.3011954497467, 52.530201581079801 ] } },
{ "type": "Feature", "properties": { "Description": "Toilette Alt-Stralau (Wendenpark) ", "isHandicappedAccessible": 1 }, "geometry": { "type": "Point", "coordinates": [ 13.478488412237899, 52.4920379163595 ] } },
{ "type": "Feature", "properties": { "Description": "Toilette Eingang Danziger Str./Paul-Heyse-Str.", "isHandicappedAccessible": 0 }, "geometry": { "type": "Point", "coordinates": [ 13.443544264464499, 52.529263712869998 ] } },
{ "type": "Feature", "properties": { "Description": "Toilette Zugang Wiener Str./Ratiborstr.", "isHandicappedAccessible": 0 }, "geometry": { "type": "Point", "coordinates": [ 13.4415032415752, 52.495200768218801 ] } },
{ "type": "Feature", "properties": { "Description": "Wall CT, Viktoriapark, Kreuzbergstr.", "isHandicappedAccessible": 1 }, "geometry": { "type": "Point", "coordinates": [ 13.377599754570801, 52.489356819343598 ] } },
{ "type": "Feature", "properties": { "Description": "Wall CT, Schöneberger Str.", "isHandicappedAccessible": 1 }, "geometry": { "type": "Point", "coordinates": [ 13.377877549161401, 52.502595944819298 ] } },
{ "type": "Feature", "properties": { "Description": "Wall CT, Waldeckpark, Alte Jakobstr.", "isHandicappedAccessible": 1 }, "geometry": { "type": "Point", "coordinates": [ 13.402625277346701, 52.506666077682802 ] } },
{ "type": "Feature", "properties": { "Description": "Wall CT, Görlitzer Park, Zugang", "isHandicappedAccessible": 1 }, "geometry": { "type": "Point", "coordinates": [ 13.4377054928347, 52.497195183710403 ] } },
{ "type": "Feature", "properties": { "Description": "Wall CT, Görlitzer Park, Zugang", "isHandicappedAccessible": 1 }, "geometry": { "type": "Point", "coordinates": [ 13.4321678831011, 52.499099294142397 ] } },
{ "type": "Feature", "properties": { "Description": "Wall CT, Petersburger Platz, Straßmannstr.", "isHandicappedAccessible": 1 }, "geometry": { "type": "Point", "coordinates": [ 13.449950159905301, 52.522068695711297 ] } },
{ "type": "Feature", "properties": { "Description": "Wall CT, Barnetstr.", "isHandicappedAccessible": 1 }, "geometry": { "type": "Point", "coordinates": [ 13.3961246058486, 52.396914512397601 ] } },
{ "type": "Feature", "properties": { "Description": "Wall CT, Dominicusstr.", "isHandicappedAccessible": 1 }, "geometry": { "type": "Point", "coordinates": [ 13.3467060287756, 52.482408188331398 ] } },
{ "type": "Feature", "properties": { "Description": "Wall CT, Warschauer Str.", "isHandicappedAccessible": 1 }, "geometry": { "type": "Point", "coordinates": [ 13.4469624913089, 52.503376593547301 ] } },
{ "type": "Feature", "properties": { "Description": "Wall CT, Edinburger Str.", "isHandicappedAccessible": 1 }, "geometry": { "type": "Point", "coordinates": [ 13.3483289012, 52.556111291699999 ] } },
{ "type": "Feature", "properties": { "Description": "Wall CT, Kranoldplatz, Bendastr.", "isHandicappedAccessible": 1 }, "geometry": { "type": "Point", "coordinates": [ 13.4368558397, 52.466167664799997 ] } },
{ "type": "Feature", "properties": { "Description": "Wall CT, Möllendorffstr.", "isHandicappedAccessible": 1 }, "geometry": { "type": "Point", "coordinates": [ 13.4795858138, 52.518999597 ] } },
{ "type": "Feature", "properties": { "Description": "Wall CT, Rennbahnstr.", "isHandicappedAccessible": 1 }, "geometry": { "type": "Point", "coordinates": [ 13.4658943730161, 52.5571969543997 ] } },
{ "type": "Feature", "properties": { "Description": "Wall CT, Bosepark, Manteuffelstr.", "isHandicappedAccessible": 1 }, "geometry": { "type": "Point", "coordinates": [ 13.377623, 52.463965 ] } },
{ "type": "Feature", "properties": { "Description": "Wall CT, Admiralbrücke, Planufer", "isHandicappedAccessible": 1 }, "geometry": { "type": "Point", "coordinates": [ 13.414421750092099, 52.494959396234599 ] } },
{ "type": "Feature", "properties": { "Description": "Wall CT, Freizeitpark Tegel an der Malche, Campestr. ", "isHandicappedAccessible": 1 }, "geometry": { "type": "Point", "coordinates": [ 13.269153981267999, 52.592675247471398 ] } },
{ "type": "Feature", "properties": { "Description": "Wall CT, Alt-Gatow", "isHandicappedAccessible": 1 }, "geometry": { "type": "Point", "coordinates": [ 13.184231473436499, 52.48414672354 ] } },
{ "type": "Feature", "properties": { "Description": "Wall CT, Heerstr.", "isHandicappedAccessible": 1 }, "geometry": { "type": "Point", "coordinates": [ 13.194803841480301, 52.513200105548499 ] } },
{ "type": "Feature", "properties": { "Description": "Wall CT, Rummelsburger Str.", "isHandicappedAccessible": 1 }, "geometry": { "type": "Point", "coordinates": [ 13.504235065463799, 52.502471865153801 ] } },
{ "type": "Feature", "properties": { "Description": "Wall CT, Roederplatz ", "isHandicappedAccessible": 1 }, "geometry": { "type": "Point", "coordinates": [ 13.480592846448801, 52.527335076607798 ] } },
{ "type": "Feature", "properties": { "Description": "Wall CT, Waldowstr.", "isHandicappedAccessible": 1 }, "geometry": { "type": "Point", "coordinates": [ 13.4856132711725, 52.548086299580902 ] } },
{ "type": "Feature", "properties": { "Description": "Wall CT, Niederneuendorfer Allee", "isHandicappedAccessible": 1 }, "geometry": { "type": "Point", "coordinates": [ 13.2107808968145, 52.567381786173399 ] } },
{ "type": "Feature", "properties": { "Description": "Wall CT, Gärtnereiring", "isHandicappedAccessible": 1 }, "geometry": { "type": "Point", "coordinates": [ 13.1464795858559, 52.523752327241198 ] } },
{ "type": "Feature", "properties": { "Description": "Wall CT, Swinemünder Str.", "isHandicappedAccessible": 1 }, "geometry": { "type": "Point", "coordinates": [ 13.3990246522732, 52.541423949649896 ] } },
{ "type": "Feature", "properties": { "Description": "Wall CT, Schönleinstr.", "isHandicappedAccessible": 1 }, "geometry": { "type": "Point", "coordinates": [ 13.4206793049899, 52.491766105592902 ] } },
{ "type": "Feature", "properties": { "Description": "Wall CT, Hermann-Dorner-Allee", "isHandicappedAccessible": 1 }, "geometry": { "type": "Point", "coordinates": [ 13.520148606444399, 52.433990200295497 ] } },
{ "type": "Feature", "properties": { "Description": "Wall CT, Fasanerie", "isHandicappedAccessible": 1 }, "geometry": { "type": "Point", "coordinates": [ 13.364716061631899, 52.607448082172802 ] } },
{ "type": "Feature", "properties": { "Description": "Wall CT, Alt-Buckow", "isHandicappedAccessible": 1 }, "geometry": { "type": "Point", "coordinates": [ 13.432928299519199, 52.422148266428302 ] } },
{ "type": "Feature", "properties": { "Description": "Wall CT, Franz-Neumann-Platz, Pankower Allee", "isHandicappedAccessible": 1 }, "geometry": { "type": "Point", "coordinates": [ 13.3648361228867, 52.563630422390197 ] } },
{ "type": "Feature", "properties": { "Description": "Wall CT, Nettelbeckplatz, Gerichtstr.", "isHandicappedAccessible": 1 }, "geometry": { "type": "Point", "coordinates": [ 13.3685793952837, 52.5448781562188 ] } },
{ "type": "Feature", "properties": { "Description": "Wall CT, Hansaplatz, Altonaer Str.", "isHandicappedAccessible": 1 }, "geometry": { "type": "Point", "coordinates": [ 13.340582308757901, 52.518103395510998 ] } },
{ "type": "Feature", "properties": { "Description": "Wall CT, Lietzenseepark, Kaiserdamm", "isHandicappedAccessible": 1 }, "geometry": { "type": "Point", "coordinates": [ 13.2909287253553, 52.510254119733503 ] } },
{ "type": "Feature", "properties": { "Description": "Wall CT, Stuttgarter Platz", "isHandicappedAccessible": 1 }, "geometry": { "type": "Point", "coordinates": [ 13.3015037506634, 52.505142665770201 ] } },
{ "type": "Feature", "properties": { "Description": "Wall CT, Sundgauer Str.", "isHandicappedAccessible": 1 }, "geometry": { "type": "Point", "coordinates": [ 13.274649654847799, 52.435233674884202 ] } },
{ "type": "Feature", "properties": { "Description": "Wall CT, Onkel-Tom-Str.", "isHandicappedAccessible": 1 }, "geometry": { "type": "Point", "coordinates": [ 13.251766385841901, 52.4489334009141 ] } },
{ "type": "Feature", "properties": { "Description": "Wall CT, Argentinische Allee", "isHandicappedAccessible": 1 }, "geometry": { "type": "Point", "coordinates": [ 13.269614775171, 52.450907180621201 ] } },
{ "type": "Feature", "properties": { "Description": "Wall CT, An der Wuhle", "isHandicappedAccessible": 1 }, "geometry": { "type": "Point", "coordinates": [ 13.5667049289231, 52.486881519005301 ] } },
{ "type": "Feature", "properties": { "Description": "Wall CT, Köpenicker Str.", "isHandicappedAccessible": 1 }, "geometry": { "type": "Point", "coordinates": [ 13.559874406879199, 52.479460808785802 ] } },
{ "type": "Feature", "properties": { "Description": "Wall CT, Weinbergspark, Veteranenstr.", "isHandicappedAccessible": 1 }, "geometry": { "type": "Point", "coordinates": [ 13.4010517818427, 52.5330296726165 ] } },
{ "type": "Feature", "properties": { "Description": "Wall CT, Böcklerpark, Prinzenstr.", "isHandicappedAccessible": 1 }, "geometry": { "type": "Point", "coordinates": [ 13.4067533804192, 52.496718551389201 ] } },
{ "type": "Feature", "properties": { "Description": "Wall CT, Lohmühleninsel, Lohmühlenstr.", "isHandicappedAccessible": 1 }, "geometry": { "type": "Point", "coordinates": [ 13.4494981765747, 52.496669769287102 ] } },
{ "type": "Feature", "properties": { "Description": "Wall CT, Alt-Stralau, Tunnelstr.", "isHandicappedAccessible": 1 }, "geometry": { "type": "Point", "coordinates": [ 13.480901493461801, 52.490020957292501 ] } },
{ "type": "Feature", "properties": { "Description": "Wall CT, Kienbergpark, Hellersdorfer Str.", "isHandicappedAccessible": 1 }, "geometry": { "type": "Point", "coordinates": [ 13.591023681430601, 52.531338663636198 ] } },
{ "type": "Feature", "properties": { "Description": "Wall CT, Schönagelstr.", "isHandicappedAccessible": 1 }, "geometry": { "type": "Point", "coordinates": [ 13.5701669923751, 52.548519869510798 ] } },
{ "type": "Feature", "properties": { "Description": "Wall CT, Schleidenplatz, Waldeyerstr.", "isHandicappedAccessible": 1 }, "geometry": { "type": "Point", "coordinates": [ 13.472649347097001, 52.5156735344464 ] } },
{ "type": "Feature", "properties": { "Description": "Wall CT, Heinrich-Heine-Str.", "isHandicappedAccessible": 1 }, "geometry": { "type": "Point", "coordinates": [ 13.413904328757599, 52.508265817048702 ] } },
{ "type": "Feature", "properties": { "Description": "Wall CT, Sellerpark, Sellerstr.", "isHandicappedAccessible": 1 }, "geometry": { "type": "Point", "coordinates": [ 13.365743504824, 52.537156769343603 ] } },
{ "type": "Feature", "properties": { "Description": "Wall CT, Ratsgasse (Marktplatz-Fußgängerzone)", "isHandicappedAccessible": 1 }, "geometry": { "type": "Point", "coordinates": [ 13.17765, 52.68761 ] } },
{ "type": "Feature", "properties": { "Description": "Wall CT, Soldiner Str.", "isHandicappedAccessible": 1 }, "geometry": { "type": "Point", "coordinates": [ 13.383639774732901, 52.559323179666002 ] } },
{ "type": "Feature", "properties": { "Description": "Wall CT, Ostender Str.", "isHandicappedAccessible": 1 }, "geometry": { "type": "Point", "coordinates": [ 13.3522985517933, 52.546270897640902 ] } },
{ "type": "Feature", "properties": { "Description": "Wall CT, Dianaplatz, Dianastr.", "isHandicappedAccessible": 1 }, "geometry": { "type": "Point", "coordinates": [ 13.312223524878, 52.606158353385702 ] } },
{ "type": "Feature", "properties": { "Description": "Wall CT, Konrad-Wolf-Str.", "isHandicappedAccessible": 1 }, "geometry": { "type": "Point", "coordinates": [ 13.4813166509108, 52.538872738265503 ] } },
{ "type": "Feature", "properties": { "Description": "Wall CT, Südstern", "isHandicappedAccessible": 1 }, "geometry": { "type": "Point", "coordinates": [ 13.4073584199877, 52.489493587630101 ] } },
{ "type": "Feature", "properties": { "Description": "Wall CT, Meierottostr.", "isHandicappedAccessible": 1 }, "geometry": { "type": "Point", "coordinates": [ 13.329973553889101, 52.496747225980698 ] } },
{ "type": "Feature", "properties": { "Description": "Wall CT, Winterfeldtplatz, Gleditschstr.", "isHandicappedAccessible": 1 }, "geometry": { "type": "Point", "coordinates": [ 13.355023, 52.496171 ] } },
{ "type": "Feature", "properties": { "Description": "Wall CT, Alt-Lübars", "isHandicappedAccessible": 1 }, "geometry": { "type": "Point", "coordinates": [ 13.358713469070899, 52.620984829518498 ] } },
{ "type": "Feature", "properties": { "Description": "Wall CT, Dolgenseestr.", "isHandicappedAccessible": 1 }, "geometry": { "type": "Point", "coordinates": [ 13.507572741953901, 52.492378564871998 ] } },
{ "type": "Feature", "properties": { "Description": "Wall CT, Dr.-Ilse-Kassel-Platz, Schloßstr.", "isHandicappedAccessible": 1 }, "geometry": { "type": "Point", "coordinates": [ 13.313359320145899, 52.616970900811097 ] } },
{ "type": "Feature", "properties": { "Description": "Wall CT, Oberbaumstr.", "isHandicappedAccessible": 1 }, "geometry": { "type": "Point", "coordinates": [ 13.4434936687943, 52.500842056772001 ] } },
{ "type": "Feature", "properties": { "Description": "Wall CT, Sportforum, Weißenseer Weg", "isHandicappedAccessible": 1 }, "geometry": { "type": "Point", "coordinates": [ 13.4723838740929, 52.537874206581201 ] } },
{ "type": "Feature", "properties": { "Description": "Wall CT, Crellemarkt, Großgörschenstr.", "isHandicappedAccessible": 1 }, "geometry": { "type": "Point", "coordinates": [ 13.3658619399184, 52.491318920437401 ] } },
{ "type": "Feature", "properties": { "Description": "Wall CT, Alt-Köpenick", "isHandicappedAccessible": 1 }, "geometry": { "type": "Point", "coordinates": [ 13.5738106656173, 52.445326176449903 ] } },
{ "type": "Feature", "properties": { "Description": "Wall CT, Egon-Erwin-Kisch-Str.", "isHandicappedAccessible": 1 }, "geometry": { "type": "Point", "coordinates": [ 13.5134186492035, 52.5677931494833 ] } },
{ "type": "Feature", "properties": { "Description": "Wall CT, Gothaer Str.", "isHandicappedAccessible": 1 }, "geometry": { "type": "Point", "coordinates": [ 13.5889935903744, 52.539603636343401 ] } },
{ "type": "Feature", "properties": { "Description": "Wall CT, Afrikanische Str.", "isHandicappedAccessible": 1 }, "geometry": { "type": "Point", "coordinates": [ 13.3365372138437, 52.552640883501901 ] } },
{ "type": "Feature", "properties": { "Description": "Wall CT, Grüntaler Str.", "isHandicappedAccessible": 1 }, "geometry": { "type": "Point", "coordinates": [ 13.393609813246499, 52.556372535753802 ] } },
{ "type": "Feature", "properties": { "Description": "Wall CT, Volkspark Hasenheide", "isHandicappedAccessible": 1 }, "geometry": { "type": "Point", "coordinates": [ 13.4171361642608, 52.4844544115752 ] } },
{ "type": "Feature", "properties": { "Description": "Wall CT, Emma-Ihrer-Str.", "isHandicappedAccessible": 1 }, "geometry": { "type": "Point", "coordinates": [ 13.4786084171703, 52.497504458766599 ] } },
{ "type": "Feature", "properties": { "Description": "Wall CT, Schützenstr.", "isHandicappedAccessible": 1 }, "geometry": { "type": "Point", "coordinates": [ 13.2102945837695, 52.550150189477698 ] } },
{ "type": "Feature", "properties": { "Description": "Wall CT, Unter den Linden", "isHandicappedAccessible": 1 }, "geometry": { "type": "Point", "coordinates": [ 13.381269454956101, 52.516609191894503 ] } },
{ "type": "Feature", "properties": { "Description": "Toilette Gutsmuthsweg", "isHandicappedAccessible": 0 }, "geometry": { "type": "Point", "coordinates": [ 13.2435201, 52.512991 ] } },
{ "type": "Feature", "properties": { "Description": "Toilette Gutsmuthsweg (Eingang Hockey-Stadion)", "isHandicappedAccessible": 0 }, "geometry": { "type": "Point", "coordinates": [ 13.24459, 52.51562 ] } },
{ "type": "Feature", "properties": { "Description": "Toilette Coubertinplatz", "isHandicappedAccessible": 0 }, "geometry": { "type": "Point", "coordinates": [ 13.240781, 52.5121801 ] } },
{ "type": "Feature", "properties": { "Description": "Toilette Eingang Reithalle / Tunnelweg", "isHandicappedAccessible": 0 }, "geometry": { "type": "Point", "coordinates": [ 13.23694025, 52.51064618 ] } },
{ "type": "Feature", "properties": { "Description": "Toilette U-Bhf. Olympia-Stadion", "isHandicappedAccessible": 0 }, "geometry": { "type": "Point", "coordinates": [ 13.24938, 52.51746 ] } },
{ "type": "Feature", "properties": { "Description": "Toilette Osnabrücker Str.", "isHandicappedAccessible": 1 }, "geometry": { "type": "Point", "coordinates": [ 13.3043888888889, 52.525527777777803 ] } },
{ "type": "Feature", "properties": { "Description": "Toilette Budapester Str.", "isHandicappedAccessible": 1 }, "geometry": { "type": "Point", "coordinates": [ 13.3361111111111, 52.504944444444398 ] } },
{ "type": "Feature", "properties": { "Description": "Toilette Joachimsthaler Str.", "isHandicappedAccessible": 0 }, "geometry": { "type": "Point", "coordinates": [ 13.3308611111111, 52.503333333333302 ] } },
{ "type": "Feature", "properties": { "Description": "Toilette Olympischer Platz", "isHandicappedAccessible": 0 }, "geometry": { "type": "Point", "coordinates": [ 13.2440277777778, 52.514222222222202 ] } },
{ "type": "Feature", "properties": { "Description": "Toilette Glockenturmstr. 1", "isHandicappedAccessible": 0 }, "geometry": { "type": "Point", "coordinates": [ 13.230638888888899, 52.513611111111103 ] } },
{ "type": "Feature", "properties": { "Description": "Toilette Reichsstr.", "isHandicappedAccessible": 0 }, "geometry": { "type": "Point", "coordinates": [ 13.272577, 52.509679 ] } },
{ "type": "Feature", "properties": { "Description": "Toilette Aßmannstr. (Marktplatz Friedrichshagen)", "isHandicappedAccessible": 1 }, "geometry": { "type": "Point", "coordinates": [ 13.6245833333333, 52.450666666666699 ] } },
{ "type": "Feature", "properties": { "Description": "Toilette Spielplatz", "isHandicappedAccessible": 0 }, "geometry": { "type": "Point", "coordinates": [ 13.3778611111111, 52.4875 ] } },
{ "type": "Feature", "properties": { "Description": "Toilette", "isHandicappedAccessible": 1 }, "geometry": { "type": "Point", "coordinates": [ 13.412954, 52.521463 ] } },
{ "type": "Feature", "properties": { "Description": "Toilette Spandauer Str. (ggü. Nikolaiviertel)", "isHandicappedAccessible": 1 }, "geometry": { "type": "Point", "coordinates": [ 13.406416666666701, 52.518472222222201 ] } },
{ "type": "Feature", "properties": { "Description": "Toilette Gutschmidtstr. (am U-Bhf.)", "isHandicappedAccessible": 0 }, "geometry": { "type": "Point", "coordinates": [ 13.4473888888889, 52.437361111111102 ] } },
{ "type": "Feature", "properties": { "Description": "Toilette Sonnenallee", "isHandicappedAccessible": 0 }, "geometry": { "type": "Point", "coordinates": [ 13.438239, 52.482874 ] } },
{ "type": "Feature", "properties": { "Description": "Toilette Residenzstr.", "isHandicappedAccessible": 0 }, "geometry": { "type": "Point", "coordinates": [ 13.363805555555601, 52.564166666666701 ] } },
{ "type": "Feature", "properties": { "Description": "Toilette Burscheider Weg", "isHandicappedAccessible": 1 }, "geometry": { "type": "Point", "coordinates": [ 13.2382777777778, 52.544472222222197 ] } },
{ "type": "Feature", "properties": { "Description": "Toilette Quellweg", "isHandicappedAccessible": 0 }, "geometry": { "type": "Point", "coordinates": [ 13.2698888888889, 52.537847222222197 ] } },
{ "type": "Feature", "properties": { "Description": "Toilette Obstallee", "isHandicappedAccessible": 1 }, "geometry": { "type": "Point", "coordinates": [ 13.163166666666701, 52.52125 ] } },
{ "type": "Feature", "properties": { "Description": "Toilette Breite Str.", "isHandicappedAccessible": 1 }, "geometry": { "type": "Point", "coordinates": [ 13.205486111111099, 52.5376388888889 ] } },
{ "type": "Feature", "properties": { "Description": "Toilette Breite Str.", "isHandicappedAccessible": 1 }, "geometry": { "type": "Point", "coordinates": [ 13.205027777777801, 52.536861111111101 ] } },
{ "type": "Feature", "properties": { "Description": "Toilette Holbeinstr. (Ludwig-Beck-Platz)", "isHandicappedAccessible": 0 }, "geometry": { "type": "Point", "coordinates": [ 13.3120833333333, 52.442666666666703 ] } },
{ "type": "Feature", "properties": { "Description": "Toilette Oswald-Schumann-Platz (Tiergarten)", "isHandicappedAccessible": 0 }, "geometry": { "type": "Point", "coordinates": [ 13.345222222222199, 52.515555555555601 ] } },
{ "type": "Feature", "properties": { "Description": "Toilette Großer Stern", "isHandicappedAccessible": 0 }, "geometry": { "type": "Point", "coordinates": [ 13.348416666666701, 52.514236111111103 ] } },
{ "type": "Feature", "properties": { "Description": "Toilette Konstanzer Str.", "isHandicappedAccessible": 1 }, "geometry": { "type": "Point", "coordinates": [ 13.310916, 52.493104 ] } },
{ "type": "Feature", "properties": { "Description": "Toilette Livländische Str.", "isHandicappedAccessible": 0 }, "geometry": { "type": "Point", "coordinates": [ 13.326417, 52.48288 ] } },
{ "type": "Feature", "properties": { "Description": "Toilette Anlegestelle Wannsee (hi. Kronprinzessinenweg)", "isHandicappedAccessible": 1 }, "geometry": { "type": "Point", "coordinates": [ 13.176222222222201, 52.421472222222199 ] } },
{ "type": "Feature", "properties": { "Description": "Toilette Arndtstr.", "isHandicappedAccessible": 0 }, "geometry": { "type": "Point", "coordinates": [ 13.3909027777778, 52.488527777777797 ] } },
{ "type": "Feature", "properties": { "Description": "Toilette Karl-Marx-Str.", "isHandicappedAccessible": 0 }, "geometry": { "type": "Point", "coordinates": [ 13.4413888888889, 52.471555555555597 ] } },
{ "type": "Feature", "properties": { "Description": "Toilette Fellbacher Str.", "isHandicappedAccessible": 0 }, "geometry": { "type": "Point", "coordinates": [ 13.3076111111111, 52.616138888888898 ] } },
{ "type": "Feature", "properties": { "Description": "Toilette Schloßstr.", "isHandicappedAccessible": 0 }, "geometry": { "type": "Point", "coordinates": [ 13.283026, 52.590697 ] } },
{ "type": "Feature", "properties": { "Description": "Toilette Mariendorfer Damm", "isHandicappedAccessible": 0 }, "geometry": { "type": "Point", "coordinates": [ 13.386907, 52.438695 ] } },
{ "type": "Feature", "properties": { "Description": "Toilette Havelberger Str.", "isHandicappedAccessible": 0 }, "geometry": { "type": "Point", "coordinates": [ 13.347013888888901, 52.533527777777799 ] } },
{ "type": "Feature", "properties": { "Description": "Toilette Oldenburger Str.", "isHandicappedAccessible": 0 }, "geometry": { "type": "Point", "coordinates": [ 13.336777777777799, 52.5332222222222 ] } },
{ "type": "Feature", "properties": { "Description": "Toilette Kiautschoustr.", "isHandicappedAccessible": 0 }, "geometry": { "type": "Point", "coordinates": [ 13.35325, 52.539902777777797 ] } },
{ "type": "Feature", "properties": { "Description": "Toilette Scholzplatz stew. (ex. Scholzplatz)", "isHandicappedAccessible": 0 }, "geometry": { "type": "Point", "coordinates": [ 13.227638888888899, 52.5065 ] } },
{ "type": "Feature", "properties": { "Description": "Toilette Wilmersdorfer Str. staw. (Parkplatz)", "isHandicappedAccessible": 0 }, "geometry": { "type": "Point", "coordinates": [ 13.3067361111111, 52.510166666666699 ] } },
{ "type": "Feature", "properties": { "Description": "Toilette Haus Nr. 63-65 (Badestelle Saatwinkel) (ex. Saatwinkel)", "isHandicappedAccessible": 0 }, "geometry": { "type": "Point", "coordinates": [ 13.2465277777778, 52.561666666666703 ] } },
{ "type": "Feature", "properties": { "Description": "Toilette verlängerte Sterkrader Str.", "isHandicappedAccessible": 0 }, "geometry": { "type": "Point", "coordinates": [ 13.2855277777778, 52.570777777777799 ] } },
{ "type": "Feature", "properties": { "Description": "Toilette Zufahrt Insel Scharfenberg/Freibad Tegeler See (ex. Strandbad Tegel)", "isHandicappedAccessible": 0 }, "geometry": { "type": "Point", "coordinates": [ 13.243222222222199, 52.576 ] } },
{ "type": "Feature", "properties": { "Description": "Toilette Revierförsterei Tegelsee/Parkplatz (ex. Revierförsterei Tegel Schwarzer Weg)", "isHandicappedAccessible": 0 }, "geometry": { "type": "Point", "coordinates": [ 13.2538055555556, 52.5853888888889 ] } },
{ "type": "Feature", "properties": { "Description": "Toilette Uferweg (Große Badewiese) (ex. Große Badewiese/Waldschluchtpfad)", "isHandicappedAccessible": 0 }, "geometry": { "type": "Point", "coordinates": [ 13.181555555555599, 52.469833333333298 ] } },
{ "type": "Feature", "properties": { "Description": "Toilette Haus Nr. 15 (ex. Groß Glienicker See/Badewiese)", "isHandicappedAccessible": 0 }, "geometry": { "type": "Point", "coordinates": [ 13.119, 52.4711944444445 ] } },
{ "type": "Feature", "properties": { "Description": "Toilette Im Dohl (Groß Glienicker See/DLRG-Wasserrettungsstation) (ex. Groß Glienicker See/Pferdek.)", "isHandicappedAccessible": 0 }, "geometry": { "type": "Point", "coordinates": [ 13.115458333333301, 52.46125 ] } },
{ "type": "Feature", "properties": { "Description": "Toilette Bürgerablage (Badestelle)", "isHandicappedAccessible": 0 }, "geometry": { "type": "Point", "coordinates": [ 13.2100833333333, 52.5852222222222 ] } },
{ "type": "Feature", "properties": { "Description": "Toilette Uferpromenade (ex. Aalemannkanal)", "isHandicappedAccessible": 0 }, "geometry": { "type": "Point", "coordinates": [ 13.2191666666667, 52.575388888888902 ] } },
{ "type": "Feature", "properties": { "Description": "Toilette Tiergarten-Unterschleuse (ex. Tiergarten Schleuse)", "isHandicappedAccessible": 0 }, "geometry": { "type": "Point", "coordinates": [ 13.3367222222222, 52.512611111111099 ] } },
{ "type": "Feature", "properties": { "Description": "Toilette Spreeweg (Tiergarten Spielplatz) (ex. Tiergarten Spielplatz)", "isHandicappedAccessible": 0 }, "geometry": { "type": "Point", "coordinates": [ 13.3566388888889, 52.5163333333333 ] } },
{ "type": "Feature", "properties": { "Description": "Toilette Transvaalstr. (Plötzensee/Volkspark Rehberge) (ex. Dohnagestell / Plötzensee)", "isHandicappedAccessible": 0 }, "geometry": { "type": "Point", "coordinates": [ 13.329972222222199, 52.546722222222201 ] } },
{ "type": "Feature", "properties": { "Description": "Toilette Hüttenweg/AVUS A115", "isHandicappedAccessible": 0 }, "geometry": { "type": "Point", "coordinates": [ 13.23525, 52.468972222222199 ] } },
{ "type": "Feature", "properties": { "Description": "Toilette (Wanderwegekreuzung mit Umgehungschaussee) (ex.Grunewaldsee Ost)", "isHandicappedAccessible": 0 }, "geometry": { "type": "Point", "coordinates": [ 13.266111111111099, 52.471805555555598 ] } },
{ "type": "Feature", "properties": { "Description": "Toilette Parkplatz Lieper Bucht (ex. Lieper Bucht/Parkplatz Havelchaussee)", "isHandicappedAccessible": 0 }, "geometry": { "type": "Point", "coordinates": [ 13.198166666666699, 52.4695 ] } },
{ "type": "Feature", "properties": { "Description": "Toilette Friedenthalpark (Badewiese Halensee) (ex. Halensee/Badewiese)", "isHandicappedAccessible": 0 }, "geometry": { "type": "Point", "coordinates": [ 13.283333333333299, 52.495611111111103 ] } },
{ "type": "Feature", "properties": { "Description": "Toilette Neuer Schildhornweg (Badewiese Teufelssee) (ex. Teufelssee)", "isHandicappedAccessible": 0 }, "geometry": { "type": "Point", "coordinates": [ 13.234694444444401, 52.489527777777802 ] } },
{ "type": "Feature", "properties": { "Description": "Toilette Parkplatz Große Steinlake", "isHandicappedAccessible": 0 }, "geometry": { "type": "Point", "coordinates": [ 13.1898888888889, 52.454583333333296 ] } },
{ "type": "Feature", "properties": { "Description": "Toilette Wasserrettungsstation Heckeshorn/Großer Wannsee", "isHandicappedAccessible": 0 }, "geometry": { "type": "Point", "coordinates": [ 13.1650555555556, 52.434805555555499 ] } },
{ "type": "Feature", "properties": { "Description": "Toilette Pfaueninselchaussee (Wasserrettungsstation Jagen 97)", "isHandicappedAccessible": 0 }, "geometry": { "type": "Point", "coordinates": [ 13.1294166666667, 52.429388888888901 ] } },
{ "type": "Feature", "properties": { "Description": "Toilette Heuweg (Wasserrettungsstation Alter Hof/Jagen 95)", "isHandicappedAccessible": 0 }, "geometry": { "type": "Point", "coordinates": [ 13.143222222222199, 52.432416666666697 ] } },
{ "type": "Feature", "properties": { "Description": "Toilette Parkplatz Südufer Krumme Lanke", "isHandicappedAccessible": 0 }, "geometry": { "type": "Point", "coordinates": [ 13.2288333333333, 52.44775 ] } },
{ "type": "Feature", "properties": { "Description": "Toilette Paul-Ernst-Park (Schlachtensee)", "isHandicappedAccessible": 0 }, "geometry": { "type": "Point", "coordinates": [ 13.2154722222222, 52.440777777777797 ] } },
{ "type": "Feature", "properties": { "Description": "Toilette Schönhauser Allee", "isHandicappedAccessible": 0 }, "geometry": { "type": "Point", "coordinates": [ 13.412888888888901, 52.532444444444401 ] } },
{ "type": "Feature", "properties": { "Description": "Toilette Haus Nr. 59 (Badestelle/Rettungsstelle Havel) (ex. Heiligensee/Badewiese)", "isHandicappedAccessible": 0 }, "geometry": { "type": "Point", "coordinates": [ 13.2215555555556, 52.594361111111098 ] } },
{ "type": "Feature", "properties": { "Description": "Toilette Dr.-Kleusberg-Promenade", "isHandicappedAccessible": 0 }, "geometry": { "type": "Point", "coordinates": [ 13.18521, 52.50165 ] } },
{ "type": "Feature", "properties": { "Description": "Toilette Am Denkmal für die ermordeten Juden Europas (Hannah-Arendt-Straße | Ecke Cora-Berliner-Straße) ", "isHandicappedAccessible": 1 }, "geometry": { "type": "Point", "coordinates": [ 13.38045, 52.51376 ] } },
{ "type": "Feature", "properties": { "Description": "Toilette Tempelhofer Feld", "isHandicappedAccessible": 0 }, "geometry": { "type": "Point", "coordinates": [ 13.40874, 52.4793 ] } },
{ "type": "Feature", "properties": { "Description": "Toilette Friedhof Heerstraße (an der Friedhofskapelle)", "isHandicappedAccessible": 0 }, "geometry": { "type": "Point", "coordinates": [ 13.2490780297724, 52.514882501201797 ] } },
{ "type": "Feature", "properties": { "Description": "Toilette Friedhof Ruhleben (altes Verwaltungsgebäude)", "isHandicappedAccessible": 0 }, "geometry": { "type": "Point", "coordinates": [ 13.23108, 52.525284 ] } },
{ "type": "Feature", "properties": { "Description": "Toilette Friedhof Heerstraße (Eingangsbereich Insterburgallee)", "isHandicappedAccessible": 0 }, "geometry": { "type": "Point", "coordinates": [ 13.253641, 52.512298 ] } },
{ "type": "Feature", "properties": { "Description": "Toilette Friedhof Grunewald", "isHandicappedAccessible": 1 }, "geometry": { "type": "Point", "coordinates": [ 13.285584, 52.49824 ] } },
{ "type": "Feature", "properties": { "Description": "Toilette Wannsee (Sommerbetrieb)", "isHandicappedAccessible": 0 }, "geometry": { "type": "Point", "coordinates": [ 13.17935, 52.43684 ] } },
{ "type": "Feature", "properties": { "Description": "Toilette Friedhof Schmargendorf", "isHandicappedAccessible": 0 }, "geometry": { "type": "Point", "coordinates": [ 13.292135, 52.473386 ] } },
{ "type": "Feature", "properties": { "Description": "Toilette Friedhof Wilmersdorf", "isHandicappedAccessible": 1 }, "geometry": { "type": "Point", "coordinates": [ 13.310068, 52.487212 ] } },
{ "type": "Feature", "properties": { "Description": "Toilette Fennpfuhlpark", "isHandicappedAccessible": 0 }, "geometry": { "type": "Point", "coordinates": [ 13.477011859924801, 52.529491193103198 ] } },
{ "type": "Feature", "properties": { "Description": "Toilette Rummelsburger Bucht", "isHandicappedAccessible": 0 }, "geometry": { "type": "Point", "coordinates": [ 13.4810596008142, 52.495588274509402 ] } },
{ "type": "Feature", "properties": { "Description": "Toilette Landschaftspark Herzberge", "isHandicappedAccessible": 1 }, "geometry": { "type": "Point", "coordinates": [ 13.508275387029601, 52.521760232464302 ] } },
{ "type": "Feature", "properties": { "Description": "Toilette Kienbergpark", "isHandicappedAccessible": 0 }, "geometry": { "type": "Point", "coordinates": [ 13.5894403548536, 52.530617921717699 ] } },
{ "type": "Feature", "properties": { "Description": "Toilette Rotes Rathaus", "isHandicappedAccessible": 0 }, "geometry": { "type": "Point", "coordinates": [ 13.40631, 52.51849 ] } },
{ "type": "Feature", "properties": { "Description": "Toilette Kleiner Tiergarten | Stromstraße", "isHandicappedAccessible": 0 }, "geometry": { "type": "Point", "coordinates": [ 13.34312, 52.52585 ] } },
{ "type": "Feature", "properties": { "Description": "Toilette Volkspark Rehberge, Eingang Afrikanische Straße | Ottawi Straße I Dohnagestell", "isHandicappedAccessible": 0 }, "geometry": { "type": "Point", "coordinates": [ 13.33705, 52.55272 ] } },
{ "type": "Feature", "properties": { "Description": "Toilette Hasenheide - Hasenschänke", "isHandicappedAccessible": 0 }, "geometry": { "type": "Point", "coordinates": [ 13.4165756212721, 52.482570383590598 ] } },
{ "type": "Feature", "properties": { "Description": "Toilette Leopoldplatz (Schulstraße | Turiner Straße)", "isHandicappedAccessible": 1 }, "geometry": { "type": "Point", "coordinates": [ 13.36125, 52.54789 ] } },
{ "type": "Feature", "properties": { "Description": "Toilette Friedhof Lilienthalstraße - Lilienthalstraße 7", "isHandicappedAccessible": 0 }, "geometry": { "type": "Point", "coordinates": [ 13.4083137021765, 52.486669230613998 ] } },
{ "type": "Feature", "properties": { "Description": "Toilette Friedhof Columbiadamm - Columbiadamm 122", "isHandicappedAccessible": 0 }, "geometry": { "type": "Point", "coordinates": [ 13.4084580865748, 52.480362755021297 ] } },
{ "type": "Feature", "properties": { "Description": "Toilette Friedhof Urnenhain - Leonberger Ring 54", "isHandicappedAccessible": 0 }, "geometry": { "type": "Point", "coordinates": [ 13.426446984327701, 52.428134443478299 ] } },
{ "type": "Feature", "properties": { "Description": "Toilette Friedhof Alt-Buckow - Alt-Buckow 39B", "isHandicappedAccessible": 0 }, "geometry": { "type": "Point", "coordinates": [ 13.4305749941639, 52.421477576532098 ] } },
{ "type": "Feature", "properties": { "Description": "Toilette Friedhof Koppelweg - Koppelweg 10", "isHandicappedAccessible": 0 }, "geometry": { "type": "Point", "coordinates": [ 13.4318942232256, 52.445070306189798 ] } },
{ "type": "Feature", "properties": { "Description": "Toilette Parkfriedhof Neukölln - Buckower Damm 148", "isHandicappedAccessible": 0 }, "geometry": { "type": "Point", "coordinates": [ 13.432548347899299, 52.431152229282702 ] } },
{ "type": "Feature", "properties": { "Description": "Toilette Friedhof Buschkrugallee - Buschkrugallee 38", "isHandicappedAccessible": 0 }, "geometry": { "type": "Point", "coordinates": [ 13.4462947014778, 52.460396974104 ] } },
{ "type": "Feature", "properties": { "Description": "Toilette Café im Park am Buschkrug", "isHandicappedAccessible": 0 }, "geometry": { "type": "Point", "coordinates": [ 13.451171777956899, 52.453898793029801 ] } },
{ "type": "Feature", "properties": { "Description": "Toilette Friedhof Rudow - Köpenicker Straße 131", "isHandicappedAccessible": 0 }, "geometry": { "type": "Point", "coordinates": [ 13.503957490031199, 52.4209827871531 ] } },
{ "type": "Feature", "properties": { "Description": "Toilette Kiosk im Nordpark", "isHandicappedAccessible": 0 }, "geometry": { "type": "Point", "coordinates": [ 13.5062657600599, 52.405264502602201 ] } },
{ "type": "Feature", "properties": { "Description": "Toilette Mauerpark(Erweiterung)", "isHandicappedAccessible": 0 }, "geometry": { "type": "Point", "coordinates": [ 13.4011410356316, 52.544010620300703 ] } },
{ "type": "Feature", "properties": { "Description": "Toilette Flughafensee Tegel (Bernauer/Sterkraderstr.)", "isHandicappedAccessible": 0 }, "geometry": { "type": "Point", "coordinates": [ 13.28361, 52.56961 ] } },
{ "type": "Feature", "properties": { "Description": "Toilette Franz-Neumann-Platz", "isHandicappedAccessible": 0 }, "geometry": { "type": "Point", "coordinates": [ 13.3649827687079, 52.563092080076999 ] } },
{ "type": "Feature", "properties": { "Description": "Toilette Familienfarm Lübars", "isHandicappedAccessible": 0 }, "geometry": { "type": "Point", "coordinates": [ 13.367540635471199, 52.608066317309998 ] } },
{ "type": "Feature", "properties": { "Description": "Toilette Am Kiesteich 50 (Parkplatz Gr. Spektesee)", "isHandicappedAccessible": 0 }, "geometry": { "type": "Point", "coordinates": [ 13.1648593254089, 52.548839880319598 ] } },
{ "type": "Feature", "properties": { "Description": "Toilette Landhausgarten Fraenkel", "isHandicappedAccessible": 0 }, "geometry": { "type": "Point", "coordinates": [ 13.360766798360199, 52.429230296264699 ] } },
{ "type": "Feature", "properties": { "Description": "Toilette Landschaftsfriedhof Gatow", "isHandicappedAccessible": 0 }, "geometry": { "type": "Point", "coordinates": [ 13.1547684974975, 52.4970888408983 ] } },
{ "type": "Feature", "properties": { "Description": "Toilette Friedhof in den Kisseln", "isHandicappedAccessible": 0 }, "geometry": { "type": "Point", "coordinates": [ 13.174539759648701, 52.5591910847752 ] } },
{ "type": "Feature", "properties": { "Description": "Toilette Friedhof in den Kisseln", "isHandicappedAccessible": 0 }, "geometry": { "type": "Point", "coordinates": [ 13.177242712306199, 52.555629574579399 ] } },
{ "type": "Feature", "properties": { "Description": "Toilette Friedhof in den Kisseln", "isHandicappedAccessible": 0 }, "geometry": { "type": "Point", "coordinates": [ 13.1880450308507, 52.556423924433801 ] } },
{ "type": "Feature", "properties": { "Description": "Toilette Volkspark Friedrichshain | Neuer Hain", "isHandicappedAccessible": 1 }, "geometry": { "type": "Point", "coordinates": [ 13.43486, 52.52773 ] } },
{ "type": "Feature", "properties": { "Description": "Toilette Friedhof Staaken", "isHandicappedAccessible": 0 }, "geometry": { "type": "Point", "coordinates": [ 13.132709906664701, 52.525277004591601 ] } },
{ "type": "Feature", "properties": { "Description": "Toilette Pfaueninselchaussee Rettungsstation Jagen 97", "isHandicappedAccessible": 0 }, "geometry": { "type": "Point", "coordinates": [ 13.21491, 52.44044 ] } },
{ "type": "Feature", "properties": { "Description": "Toilette Südende Schlachtensee ggü. Nr. 145", "isHandicappedAccessible": 0 }, "geometry": { "type": "Point", "coordinates": [ 13.25644, 52.43837 ] } },
{ "type": "Feature", "properties": { "Description": "Toilette Friedenstr. 8-10, 14109 Berlin", "isHandicappedAccessible": 0 }, "geometry": { "type": "Point", "coordinates": [ 13.141647892789701, 52.413632930228403 ] } },
{ "type": "Feature", "properties": { "Description": "Toilette Königin-Luise-Str. 57 (Friedhof), 14195 Berlin", "isHandicappedAccessible": 0 }, "geometry": { "type": "Point", "coordinates": [ 13.2861241807067, 52.458897304578699 ] } },
{ "type": "Feature", "properties": { "Description": "Toilette Thuner Platz 2-4 (Friedhof), 12205 Berlin", "isHandicappedAccessible": 0 }, "geometry": { "type": "Point", "coordinates": [ 13.296337090329301, 52.423442510564698 ] } },
{ "type": "Feature", "properties": { "Description": "Toilette Bergstr. 38 (Friedhof), 12169 Berlin", "isHandicappedAccessible": 0 }, "geometry": { "type": "Point", "coordinates": [ 13.3421494600363, 52.458623228751598 ] } },
{ "type": "Feature", "properties": { "Description": "Toilette Pächter der Gewerbeeinheit - (Perelsplatz 1, 12159 Berlin) während der Öffnungszeiten", "isHandicappedAccessible": 0 }, "geometry": { "type": "Point", "coordinates": [ 13.3351537042024, 52.475975546112998 ] } },
{ "type": "Feature", "properties": { "Description": "Toilette Rathaus Schöneberg,  John-F.-Kennedy-Platz", "isHandicappedAccessible": 1 }, "geometry": { "type": "Point", "coordinates": [ 13.3440246979359, 52.484798895870803 ] } },
{ "type": "Feature", "properties": { "Description": "Toilette BDG Manteuffelstraße 63 12103 Berlin", "isHandicappedAccessible": 1 }, "geometry": { "type": "Point", "coordinates": [ 13.378241338667699, 52.463987981448902 ] } },
{ "type": "Feature", "properties": { "Description": "Toilette Oranienplatz", "isHandicappedAccessible": 0 }, "geometry": { "type": "Point", "coordinates": [ 13.41514, 52.50263 ] } },
{ "type": "Feature", "properties": { "Description": "Toilette BDG Rathausstraße 27 / Kaiserstraße 10105 Berlin", "isHandicappedAccessible": 1 }, "geometry": { "type": "Point", "coordinates": [ 13.379170914689301, 52.445891739919503 ] } },
{ "type": "Feature", "properties": { "Description": "Toilette BDG  Strelitzstraße 15/17 / Machonstraße 10105 Berlin", "isHandicappedAccessible": 1 }, "geometry": { "type": "Point", "coordinates": [ 13.383063429399799, 52.449323790765803 ] } },
{ "type": "Feature", "properties": { "Description": "Toilette Pächter der Gewerbeeinheit -  (Alt-Tempelhof 21,  12103 Berlin) während der Öffnungszeiten", "isHandicappedAccessible": 0 }, "geometry": { "type": "Point", "coordinates": [ 13.385260988844299, 52.466001465142099 ] } },
{ "type": "Feature", "properties": { "Description": "Toilette Rathaus Tempelhof, Tempelhofer Damm 165", "isHandicappedAccessible": 1 }, "geometry": { "type": "Point", "coordinates": [ 13.386006542689, 52.462446950641201 ] } },
{ "type": "Feature", "properties": { "Description": "Toilette Gemeinschaftshaus Lichtenrade Barnetstraße 11, 12305 Berlin", "isHandicappedAccessible": 1 }, "geometry": { "type": "Point", "coordinates": [ 13.4055541117744, 52.394338448172498 ] } },
{ "type": "Feature", "properties": { "Description": "Toilette Rathaus Neue Krugallee 4,12435 Berlin", "isHandicappedAccessible": 1 }, "geometry": { "type": "Point", "coordinates": [ 13.480269350458, 52.483511271518402 ] } },
{ "type": "Feature", "properties": { "Description": "Toilette Friedhof Baumschulenweg Warteraum, Kiefholzstraße 221-228, 12437 Berlin", "isHandicappedAccessible": 0 }, "geometry": { "type": "Point", "coordinates": [ 13.49343, 52.46053 ] } },
{ "type": "Feature", "properties": { "Description": "Toilette Friedhof Baumschulenweg,Öffentl.", "isHandicappedAccessible": 0 }, "geometry": { "type": "Point", "coordinates": [ 13.49379, 52.46054 ] } },
{ "type": "Feature", "properties": { "Description": "Toilette Bürgeramt Michael-Brückner-Str. 1, 12439 Berlin", "isHandicappedAccessible": 1 }, "geometry": { "type": "Point", "coordinates": [ 13.510797028292, 52.456201934376601 ] } },
{ "type": "Feature", "properties": { "Description": "Toilette Mittelpunktbibliothek Michael-Brückner-Str. 9, 12439 Berlin", "isHandicappedAccessible": 0 }, "geometry": { "type": "Point", "coordinates": [ 13.5142103972727, 52.4539572010694 ] } },
{ "type": "Feature", "properties": { "Description": "Toilette Cuvrystraße", "isHandicappedAccessible": 0 }, "geometry": { "type": "Point", "coordinates": [ 13.44417, 52.49827 ] } },
{ "type": "Feature", "properties": { "Description": "Toilette Bürgerhaus Altglienicke Ortolfstr. 182-184, 12524 Berlin", "isHandicappedAccessible": 1 }, "geometry": { "type": "Point", "coordinates": [ 13.528537104640799, 52.403193380900902 ] } },
{ "type": "Feature", "properties": { "Description": "Toilette Friedh. Oberschöneweide, Verlängerte Rathenaustr. 131 a, 12459 Berlin", "isHandicappedAccessible": 0 }, "geometry": { "type": "Point", "coordinates": [ 13.53482, 52.46336 ] } },
{ "type": "Feature", "properties": { "Description": "Toilette Friedhof Adlershof, Friedlander Straße 156, 12489 Berlin", "isHandicappedAccessible": 1 }, "geometry": { "type": "Point", "coordinates": [ 13.54731, 52.44318 ] } },
{ "type": "Feature", "properties": { "Description": "Toilette Dörpfeldstr., 12849 Berlin", "isHandicappedAccessible": 1 }, "geometry": { "type": "Point", "coordinates": [ 13.548111466436801, 52.437947587397602 ] } },
{ "type": "Feature", "properties": { "Description": "Toilette Rathaus Alt - Köpenick 21,12555 Berlin", "isHandicappedAccessible": 1 }, "geometry": { "type": "Point", "coordinates": [ 13.574850602775101, 52.445753424988297 ] } },
{ "type": "Feature", "properties": { "Description": "Toilette Müggelheimer Str. 1, 12555 Berlin", "isHandicappedAccessible": 0 }, "geometry": { "type": "Point", "coordinates": [ 13.5749493222664, 52.444095825449097 ] } },
{ "type": "Feature", "properties": { "Description": "Toilette Bürgerzentrum Grünau, Wassersportallee 34, 12527 Berlin", "isHandicappedAccessible": 1 }, "geometry": { "type": "Point", "coordinates": [ 13.578205283910499, 52.415750381637402 ] } },
{ "type": "Feature", "properties": { "Description": "Toilette Mittelpunktsbibliothek Alter Markt 2, 12555 Berlin", "isHandicappedAccessible": 0 }, "geometry": { "type": "Point", "coordinates": [ 13.584514909757299, 52.446696972366198 ] } },
{ "type": "Feature", "properties": { "Description": "Toilette Friedhof Grünau, Wartebereich", "isHandicappedAccessible": 1 }, "geometry": { "type": "Point", "coordinates": [ 13.59039, 52.40715 ] } },
{ "type": "Feature", "properties": { "Description": "Toilette Friedhof Grünau öffentlich, Rabindranath-Tagore-Straße 18-20, 12527 Berlin", "isHandicappedAccessible": 1 }, "geometry": { "type": "Point", "coordinates": [ 13.59041, 52.40732 ] } },
{ "type": "Feature", "properties": { "Description": "Toilette Mariannenplatz", "isHandicappedAccessible": 1 }, "geometry": { "type": "Point", "coordinates": [ 13.42465, 52.5031 ] } },
{ "type": "Feature", "properties": { "Description": "Toilette Friedhof Müggelheim, Gosener Landstraße 1 / Im Jagen 127, 12559 Berlin", "isHandicappedAccessible": 0 }, "geometry": { "type": "Point", "coordinates": [ 13.675072349851099, 52.406628946455697 ] } },
{ "type": "Feature", "properties": { "Description": "Toilette Friedhof Rahnsdorf, Fürstenwalder Allee 93, 12589 Berlin", "isHandicappedAccessible": 1 }, "geometry": { "type": "Point", "coordinates": [ 13.69588, 52.43754 ] } },
{ "type": "Feature", "properties": { "Description": "Toilette Nahe Zoologischer Garten, Hardenbergplatz 9-11", "isHandicappedAccessible": 1 }, "geometry": { "type": "Point", "coordinates": [ 13.33262, 52.50853 ] } },
{ "type": "Feature", "properties": { "Description": "Toilette Bahnhof Friedrichstraße, Georgenstraße 14", "isHandicappedAccessible": 0 }, "geometry": { "type": "Point", "coordinates": [ 13.387249, 52.519961 ] } },
{ "type": "Feature", "properties": { "Description": "Toilette Bahnhof Alexanderplatz, Dircksenstraße 2", "isHandicappedAccessible": 1 }, "geometry": { "type": "Point", "coordinates": [ 13.411718, 52.521388 ] } },
{ "type": "Feature", "properties": { "Description": "Toilette Bahnhof Ostkreuz, Sonntagstraße 37", "isHandicappedAccessible": 1 }, "geometry": { "type": "Point", "coordinates": [ 13.467933, 52.503972 ] } },
{ "type": "Feature", "properties": { "Description": "Toilette Bahnhof Gesundbrunnen, Badstraße 1-3", "isHandicappedAccessible": 1 }, "geometry": { "type": "Point", "coordinates": [ 13.388734, 52.548889 ] } },
{ "type": "Feature", "properties": { "Description": "Toilette Gesundbrunnencenter, Badstraße 4", "isHandicappedAccessible": 1 }, "geometry": { "type": "Point", "coordinates": [ 13.38892, 52.54925 ] } },
{ "type": "Feature", "properties": { "Description": "Toilette Grunewald West, Kronprinzessinnenweg 120", "isHandicappedAccessible": 1 }, "geometry": { "type": "Point", "coordinates": [ 13.190865, 52.434313 ] } },
{ "type": "Feature", "properties": { "Description": "Toilette Bahnhof Spandau, Seegefelder Straße 1", "isHandicappedAccessible": 1 }, "geometry": { "type": "Point", "coordinates": [ 13.198235, 52.534622 ] } },
{ "type": "Feature", "properties": { "Description": "Toilette Kleiner Tiergarten | Stromstraße", "isHandicappedAccessible": 0 }, "geometry": { "type": "Point", "coordinates": [ 13.34312, 52.52585 ] } },
{ "type": "Feature", "properties": { "Description": "Toilette Bahnhof Wannsee, Kronprinzessinnenweg 250", "isHandicappedAccessible": 1 }, "geometry": { "type": "Point", "coordinates": [ 13.179287, 52.42158 ] } },
{ "type": "Feature", "properties": { "Description": "Toilette Bahnhof Südkreuz (Ost), General-Pape-Straße 1", "isHandicappedAccessible": 1 }, "geometry": { "type": "Point", "coordinates": [ 13.36582, 52.47621 ] } },
{ "type": "Feature", "properties": { "Description": "Toilette Bahnhof Südkreuz (West), Hildegard-Knef-Platz", "isHandicappedAccessible": 1 }, "geometry": { "type": "Point", "coordinates": [ 13.36418, 52.47653 ] } },
{ "type": "Feature", "properties": { "Description": "Toilette Bahnhof Potsdamer Platz, Potsdamer Platz", "isHandicappedAccessible": 1 }, "geometry": { "type": "Point", "coordinates": [ 13.37595, 52.50966 ] } },
{ "type": "Feature", "properties": { "Description": "Toilette Berlin Hauptbahnhof, Europaplatz 1", "isHandicappedAccessible": 1 }, "geometry": { "type": "Point", "coordinates": [ 13.369446, 52.524798 ] } },
{ "type": "Feature", "properties": { "Description": "Toilette Berlin Ostbahnhof, Koppenstraße 3", "isHandicappedAccessible": 1 }, "geometry": { "type": "Point", "coordinates": [ 13.435396, 52.509596 ] } },
{ "type": "Feature", "properties": { "Description": "Toilette Bahnhof Lichtenberg, Weitlingstraße 22", "isHandicappedAccessible": 1 }, "geometry": { "type": "Point", "coordinates": [ 13.497285, 52.509403 ] } },
{ "type": "Feature", "properties": { "Description": "Toilette Ehemaliger Garnisonfriedhof | Müllerstraße ", "isHandicappedAccessible": 0 }, "geometry": { "type": "Point", "coordinates": [ 13.35924, 52.54892 ] } },
{ "type": "Feature", "properties": { "Description": "Toilette Park am Gleisdreieck", "isHandicappedAccessible": 1 }, "geometry": { "type": "Point", "coordinates": [ 13.37306, 52.49629 ] } },
{ "type": "Feature", "properties": { "Description": "Toilette Park am Gleisdreieck", "isHandicappedAccessible": 1 }, "geometry": { "type": "Point", "coordinates": [ 13.3769, 52.49502 ] } },
{ "type": "Feature", "properties": { "Description": "Toilette Tempelhofer Feld", "isHandicappedAccessible": 1 }, "geometry": { "type": "Point", "coordinates": [ 13.41755, 52.47681 ] } },
{ "type": "Feature", "properties": { "Description": "Toilette Tempelhofer Feld", "isHandicappedAccessible": 1 }, "geometry": { "type": "Point", "coordinates": [ 13.41766, 52.47019 ] } },
{ "type": "Feature", "properties": { "Description": "Toilette Tempelhofer Feld", "isHandicappedAccessible": 1 }, "geometry": { "type": "Point", "coordinates": [ 13.38677, 52.4713 ] } },
{ "type": "Feature", "properties": { "Description": "Toilette Tempelhofer Feld", "isHandicappedAccessible": 1 }, "geometry": { "type": "Point", "coordinates": [ 13.40995, 52.4794 ] } },
{ "type": "Feature", "properties": { "Description": "Toilette Tempelhofer Feld", "isHandicappedAccessible": 0 }, "geometry": { "type": "Point", "coordinates": [ 13.40423, 52.4817 ] } }
]
}
